[
  {
    "kind": "Listing",
    "data": {
      "after": null,
      "dist": 1,
      "modhash": "",
      "geo_filter": "",
      "children": [
        {
          "kind": "t3",
          "data": {
            "approved_at_utc": null,
            "subreddit": "u_j259awesome",
            "selftext": "r/r4rDFW r/r4rMelbourne r/r4rSeattle r/R6SiegeFashionAdvice r/raccoongifs r/racequeens r/RaceTrackDesigns r/Rachelbushfans r/RachelMcAdams r/racing r/racistpassdenied r/radicalqueers r/Radiolab r/ragdolls r/RagenChastain r/RagnarokMEternalLove r/RagnarokOnline r/RaIn r/Rainbow6Siege r/RainbowSix r/RaiTrade r/RakanMains r/RallyPorn r/ralphthemoviemaker r/ralsei r/ram_trucks r/RamblersDen r/randomactsofamazon r/RandomActsOfBras r/RandomActsOfPegging r/RandomActsOfPolish r/RandomActsOfVinyl r/randpaul r/rangersfc r/RangersOfOblivionGTA r/rantgrumps r/Raphtalia r/RapMoreLikeCrap r/rarelobsters r/Rarethreats r/RashidaJones r/raspberryDIY r/RatchetAndClank r/Rate3 r/RateMyAudio r/RateMyButt r/RatRod r/Ravencoin r/raw r/RayDonovan r/RayHoltMemes r/razorbacks r/RBNLifeSkills r/RDR2mysteries r/readitnow r/ReadMyScript r/ReagentTesting r/Real_Estate r/RealEstatePhotography r/RealEstateTechnology r/realhousewives r/RealLifePokemon r/realms r/realsocialengineering r/RealTesla r/reasoners r/RebelTaxi r/REBL r/recipeclub r/reclassified r/recoilbutts r/recordstore r/recovery r/RecPics r/RecRoom r/recycling r/Red_Dead_Redemption_2 r/redacted r/RedactedCharts r/ReddHub r/RedditAndChill r/RedditArmie r/RedditCensors r/RedditDads r/redditguides r/RedditInsider r/redditisland r/redditlists r/RedditMinusMods r/redditoroftheday r/redditstories r/RedditVN r/redneckfixes r/RedneckGifs r/redpill r/redpillbooks r/RedPillWives r/RedPulseToken r/redrising r/RedSoccer_EPL r/Reduction r/RedvolutionOfficial r/RedWingShoes r/REEEEEE r/Referrals r/regina r/reiki r/Reincarnation r/reinforcementlearning r/RelationshipMemes r/RelationshipsOver35 r/Relax r/relaxedpokemontrades r/RelevantXKCD r/REMath r/ReneeMurden r/RenektonMains r/renfaire r/Reno r/Rento r/RepGuides r/RepLadiesBST r/reptiliandude r/republicans r/resilientcommunities r/ResinCasting r/resonatingfury r/ResponsibleRevenge r/RestaurantsThatMeme r/restaurateur r/Resume r/retailhell r/retailporn r/retardsinaction r/retiredusername r/retorted r/RetroArch r/RetroGamePorn r/retrogameswap r/RetroLibraryMusic r/Revit r/Revolvers r/RevueStarlight r/rfelectronics r/rheumatoid r/rhps r/RicardoMilosMemes r/RiCare r/RiceCookerRecipes r/rickandmorty_C137 r/rickandmortyGIFs r/Rickyisms r/riddim r/Rifftrax r/Rift r/RightwingLGBT r/RimWorldSeeds r/Ring r/ringdoorbell r/ripplers r/RippleTalk r/risa r/riseagainst r/RiseofCivilizationsEn r/RiseofKingdoms r/riskyclick r/riskyclickoftheday r/RLCustomTraining r/RnBHeads r/RoadPorn r/roastmytrack r/robac r/Robbaz r/robinhobb r/robloxgamedev r/Robocraft r/robots r/rockabilly r/RockClimbing r/RocketLab r/RodSquare r/ROH r/rojava r/roll20LFG r/rome r/romemes r/ronswanson r/roomdetective r/rootkit r/ror2 r/Rosacea r/ROTC r/RothWellden r/rotmgtradingpost r/RowlingWritings r/rpdrgonewild r/RPGhumor r/RPI r/RS3Ironmen r/RStudio r/ru r/rugby r/rugbystreams r/ruger r/Rule34FanArt r/Rule34SFM r/rule63 r/rulesofsurvival r/Runner5 r/RunnerHub r/runninglifestyle r/runthejewels r/rupaulsdragracedrama r/RussiaDenies r/RussianDoll r/rust_gamedev r/RVLiving r/RX7 r/ryerson r/RyzeMains \n\n&amp;#x200B;\n\nr/S01E01 r/S2000 r/saab r/SaaS r/Sabermetrics r/sabrina r/SabrinaCarpenter r/sadbuddyretard r/SaddestBackflip r/SAGAcomic r/SAHP r/SailboatCruising r/sailingcrew r/SaintsFC r/Sakartvelo r/saltandsanctuary r/saltyobituaries r/Salvia r/SamandTolki r/SamPepper r/Samplehunters r/SamuraiChamploo r/Sandman r/Sandwiches r/SantaBarbara r/santaclaritadiet r/santacruz r/santashelpers r/SaoirseRonan r/SAP r/SapphoAndHerFriend r/saraba1st r/SarahChalke r/SarahSnyder r/SarahStephens r/SaraMeiKasaiOfficial r/SaraMillsSecret r/sarcasm r/Satan r/satania r/satire r/satisfyinggrass r/saudelobaes r/Savage_Memes r/SavageOuija r/savageworlds r/savannah r/saxophone r/SayHenloToMyLilFren r/SBU r/sca r/scacjdiscussion r/scamslayers r/Scandal r/ScaringChildren r/Scarrapics r/SCBuildIt r/scenes r/scheme r/SchittsCreek r/Schizoid r/SCHLAND r/schnauzers r/schrutetoobig r/schweiz r/science2 r/ScienceGIFs r/ScienceNetwork r/ScienceParents r/scientificresearch r/ScientistsMarch r/Scientits r/scifi_bookclub r/SciFiConcepts r/SciFiModels r/SCJerk r/Scoobydoo r/scoreball r/ScottishFootball r/scotus r/SCPSecretLab r/ScratchyScratchy r/ScreamQueensTV r/ScreenCapsForTheSoul r/scripteddoggifs r/ScriptSwap r/scrum r/Sdorica r/seaofgreed r/searchandrescue r/secondlife r/SecondWorldProblems r/SecretSubreddit r/SecretWorldLegends r/secularbuddhism r/securityguards r/seedstock r/seedswap r/seekingsisterwifetlc r/Seethroughyogapants r/SEGA r/SEGAGENESIS r/SegaSaturn r/seiyuu r/SelenaGomezLust r/selfeducation r/SelfHarmScars r/Semenretention r/senrankagura r/SEO_Infographics r/seoul r/Sephora r/serial_killers r/serialpodcastorigins r/seriea r/SeriousFIFA r/Serverlife r/servers r/service_dogs r/SesameStreetMemes r/SETI r/SEUT r/sexmemes r/SEXONDRUGS r/sexpertslounge r/sextips r/SexyCelebFemales r/sexycelebs r/sexygames r/SexyMusicVideos r/SF_Book_Club r/SFBayHousing r/SFBayJobs r/SFWNextDoorGirls r/sfwtrees r/shacomains r/shadow_of_war r/ShadowBan r/shadowhunters r/ShadowoftheColossus r/shadowrunreturns r/ShaileneWoodley r/shakira r/shallowhouse r/shallyzsaa r/Shaneisms r/ShannanWatts r/SharePLEX r/sharkswithhumanteeth r/sharpening r/shaving r/sheetmusic r/sheffield r/ShemaleSexDolls r/Shenmue r/ShibaInu r/Shihtzu r/shills r/SHINee r/ShipwreckPorn r/ShitGoneWildSays r/ShitJadenSays r/ShitJamesSays r/ShitNsSay r/shitpostbound r/shitposting r/ShitpostXIV r/ShitRamsaySays r/ShitRimworldSays r/ShitThe_DonaldSays r/shittingadvice r/shitty_ecr r/shitty_housing r/Shittyaskflying r/ShittyBuildaPC r/shittyconspiracy r/shittycoolguides r/Shittycosplay r/shittydiy r/shittyengineering r/Shittygamecollecting r/shittypopanalysis r/ShittySeduction r/ShittySekiro r/ShittyShittyRainbow6 r/shittyshowerthoughts r/shittystockphotos r/ShittyTechDeals r/ShittyWholesomeMemes r/shittywoodworking r/shoebots r/Shoes r/shooting_stars r/shootingcars r/shoppingaddiction r/shoptours r/shorthorror r/ShortSadStories r/shortscifistories r/shortwave r/shortykeepingittight r/ShotaCops r/shoujoai r/showbox r/ShowoffsCrashingCars r/Shrekmemes r/Shrimping r/ShrineOfJonesy r/ShroomID r/ShrugLifeSyndicate r/Shuffles_Deck r/Siamesecats r/siatrader r/sidehustle r/Sidemen r/signal r/Sikh r/siliconvalley r/SilviaCaruso r/simcity4 r/simonfraser r/simpleios r/SimplySporty r/simpsonswave r/Sims3 r/SimsIRL r/Simulate r/SimulationTheory r/singedmains r/SingleParents r/singlepixelmemes r/Sinkpissers r/SinonAssOnline r/SiriFail r/Sissydating r/SISwimsuitGirls r/Siv r/sjain_guides r/Sjin r/SJSU r/SJWstories r/skam r/skatespotporn r/sketchapp r/Sketchup r/ski r/SkinCareScience r/skinsTV r/SkyFactory r/Skyforge r/SkyLine r/skylineporn r/SkyrimBuilds r/skyrimrequiem r/SkyrimSkills_IRL r/Slack r/Slackline r/slashdiablo r/slaveleia r/sleeptrain r/sleepy r/Slender_Man r/slightlyunsatisfying r/Slimemolds r/SlimmingWorld r/slingtv r/Slovenia r/SlowTV r/sludge r/Slycooper r/sm4sh r/small_business_ideas r/smallboobproblems r/SmallDogBigBed r/SmallYoutubers r/smartmirrors r/Smartphones r/smartwatch r/smashcirclejerk r/SmashingPumpkins r/smashmemes r/SMBCComics r/smitetraining r/SmithAndWesson r/smokingcrabs r/Smoothies r/smoothslowmo_nsfw r/snails r/snapchatgeofilters r/sneakerbots r/SneakyBackgroundFork r/SneakyPaws r/SnipsAir r/SNLirl r/snowing r/Snus r/soanamnesis r/soccernerd r/soccerspirits r/soccerstreams__ r/SoccerThunder r/SocialDemocracy r/Socialistart r/Socialistmusic r/socialistprogrammers r/socialjustice101 r/SocialMediaMarketing r/Soda r/sodadungeon r/softscience r/softwarearchitecture r/softwaretesting r/SolarDIY r/solarpunk r/SolusProject r/SombraMains r/sonamains r/songaweek r/SongwritingPrompts r/sonicshowerthoughts r/sony r/SonyXperia r/sooners r/SootHouse r/SOPA r/sophiknight r/Sororities r/Sorosforprison r/souleater r/SoulKnight r/SoundCloudHipHop r/sounddesign r/SoundsVintage r/Southerncharm r/SouthgateMemes r/SouthJersey r/Sovereigncitizen r/Space_Colonization r/space_settlement r/SpaceballsMemes r/spacecats r/SpaceDandy r/SpaceMusic r/SpaceVideos r/Sparkster r/spartanrace r/SpartaStartups r/Spearfishing r/SpecialAccess r/specialed r/species r/spelunky r/sphynx r/SpiceandWolf r/Spicy_Memes r/Spintires r/Splintercell r/SpongeWatch r/spooktober r/Spore r/SporeSwap r/SportingKC r/sportsjerseys r/SportsPorn r/Sprechstunde r/springfieldMO r/SpringPorn r/Sprinting r/sproing r/squash r/squidward_irl r/squirrels r/SquirrelsEatingPizza r/squishypuppers r/SR71 r/srilanka r/SRSFunny r/SRSGaming r/SSBBW_FANS r/stadiumporn r/Stand r/StandUpSpecials r/stanford r/StannisTheMantis r/Staples r/Star_Wars_Battlefront r/starbucksbaristas r/starcraft_strategy r/Starfield r/StartingStrength r/startpages r/StartupAccelerators r/StarWarsArmada r/starwarscanon r/StarWarsCantina r/starwarscomics r/StarWarsForceArena r/StarWarsTheories r/StateofDecay2 r/StateOfTheUnion r/stationery r/statuegropers r/statusim r/STD r/StealingTheShow r/Steam_Link r/SteamedHams r/steamfriend r/steamgiveaway r/SteamOS r/SteamPlay r/steamporn r/SteamReviews r/SteamTradingCards r/Steel_Division r/Steelbooks r/steemit r/StephanieRayner r/StephClaireSmith r/Stepmania r/stevedangle r/stevensuptic r/Stitchy r/stock r/stockholm r/StolenValor r/stonermetal r/stop_motion r/stopadvertising r/StopIDTheft r/StopSelfHarm r/StopSpeeding r/storiesfromapotato r/storj r/stormchasing r/StormComing r/stormtroopersinphotos r/storyofseasons r/Storyshift r/StPetersburgFL r/straightedge r/Stratis r/streaming r/streetlightmanifesto r/StreetwearSales r/Stress r/stronglifts r/Stuck10YearsBehind r/stuckgirls r/studentfood r/studentloandefaulters r/study r/studyAbroad r/studytips r/Stutter r/Sub4Sub r/Subaru_Outback r/subaruimpreza r/SublimeText r/Subliminal r/subreddit r/SubredditDramaDrama r/SubscriptionBoxes r/subsithoughtwerefake r/SuburbanFarming r/Suburbanhell r/subway r/subwaysubway r/suchislifeinmoscow r/suddenlyalabama r/SuddenlyIRealized r/SuddenlyLesbian r/Sufjan r/sugarfree r/SuicideBereavement r/Suicidegirlshopeless r/suicidology r/SummerGlau r/SummerPorn r/Summit1G r/summoners r/Sumo r/sunlesssea r/Sup r/SuperMega r/SuperMegaBaseball r/superplanetdolan r/supersentai r/SuperStarBTS r/superstarsmtown r/SurfaceGaming r/SurfaceLinux r/surpriselightsabers r/SurrealApprovals r/SurrealLore r/surrealtraa r/Surveying r/SurvivalGaming r/survivalhorror r/survivetheculling r/susancoffey r/SushiRoll r/SVU r/swachhcoin r/SwainMains r/sweatcoin r/SweaterDress r/swgemu r/swgoh_guilds r/SwingDancing r/swissalpsmining r/SWlegion r/swoletariat r/SwordAndScale r/SXSW r/SymmetraMains r/symphonicmetal r/synapseai r/Synchronicities r/Synesthesia r/synthesizercirclejerk r/synthpop r/Syracuse r/Syria r/SyrianCirclejerkWar r/SysAdminBlogs r/sysadmintools r/systemofadown r/systems \n\n&amp;#x200B;\n\nr/tabdetective r/tablets r/TabooFX r/Tachanka r/tacticalbarbell r/taekwondo r/tahoe r/taijiquan r/takecareofmyplant r/TalesFromAutoRepair r/talesfromdesigners r/TalesFromDispatch r/TalesFromEMS r/TalesFromFastFood r/TalesFromHousekeeping r/Talesfromrimworld r/TalesFromTheMilitary r/TalesFromYourBank r/TalesFromYourBarista r/TalesoftheConvention r/TaliyahMains r/TalkShowGirls r/talkshows r/TalkTherapy r/Tallahassee r/tallfashionadvice r/tampabayrays r/tanks r/tapirs r/tardcat r/taskmaster r/TattooArt r/Tau40K r/Tautology r/Taxidermy r/taxmarch r/taxpros r/taylormariehill r/TaylorMomsen r/TaylorSwiftBreasts r/Tayne r/tdi r/teachinginjapan r/teachinginkorea r/teamliquid r/TeardropTrailers r/technawwlogy r/TechnicalDeathMetal r/TechnicallyCorrect r/techsupportanimals r/TeemoTalk r/TeenAmIUgly r/TeenMFA r/teenrelationships r/teentitans r/TeenWolf r/teethdrumming r/tekkit r/telecaster r/telecommuting r/TelegramBots r/TelegramStickersShare r/televisioncirclejerk r/TelevisionPosterPorn r/TellReddit r/Tempe r/Temple r/templeofthephil r/TenYearsAgo r/tequila r/terencemckenna r/TerrariaDesign r/tesdcares r/TeslaLounge r/TeslaPorn r/test r/Tetris99 r/TexasPolitics r/TexasTech r/textdoor r/tf_irl r/TFABAARBI r/TFABLinePorn r/tfc r/ThailandTourism r/thalassaphobia r/that_Poppy r/thatcouldvebeenworse r/thatescalatedquickly r/thatsneat r/ThatsWhatSheSaid r/The48LawsOfPower r/the_darnold r/The_Dotard r/The_Europe r/The_Farage r/The_Keepers r/The_Leftorium r/the_mouse r/The_MuellerMeltdown r/The_Wall r/TheAgora r/TheArtifice r/TheB1G r/TheBeatles r/TheBigLezShow r/thebindingofisaac r/theboudoir r/TheBrightSide r/TheCannalysts r/TheChills r/TheCloneWars r/TheCompletionist r/TheCulture r/TheDarwinProject r/TheDearHunter r/TheDickShow r/thedivisionclans r/TheDogPaw r/thedoors r/TheeHive r/TheFarSide r/thefighterandthekid r/TheFrontBottoms r/thegdstudio r/TheGifted r/TheGlassCannonPodcast r/TheGreatWar r/TheGriffonsSaddlebag r/TheHearth r/theHunter r/theinternetofshit r/theJoeBuddenPodcast r/THEKEYOFFICIAL r/thelastofusfactions r/thelema r/TheLetterH r/TheMarvelousMrsMaisel r/TheMaskedSinger r/TheMassive r/ThemeParkitect r/themoddingofisaac r/themountaingoats r/TheNational r/theneedledrop r/Thenewsroom r/TheNightmareBeneath r/TheNightOf r/TheNSFWClub r/theNvidiaShield r/TheOceanCleanup r/TheOCS r/theodd1sout r/theofficegifs r/theofficememes r/TheOriginals r/TheOverload r/TheoVon r/ThePopcornStand r/therapists r/theredditor r/TheRedDress r/TheRedLion r/TheSecretWorld r/TheSimsBuilding r/thesmiths r/TheStaircase r/TheStrain r/thesuperbowl r/TheSurvivalGuide r/theticket r/theunexplained r/TheValleyFolk r/thevenomsite r/TheWaterLew r/TheWitness r/TheWolfAmongUs r/theworldnews r/theydidthemeth r/ThingsFightingIdiots r/ThingsIWishIKnew r/thirdworldproblems r/ThisCrazyBitch r/thisisntwhoweare r/thisweekinreview r/ThoseEyes r/thot_patrol r/thrashmetal r/Thrift r/ThriftyThread r/thronescomics r/thuglife r/TiADiscussion r/TIDTRT r/TigerBelly r/tightsandlooseclothes r/tijuana r/Tiki r/tildes r/timbers r/Timeless r/TimeManagement r/timeshiftedmemes r/Tinderpickuplines r/tinytower r/tiodopave r/tipoftheday r/Titanfall_2_ r/TLCsisterwives r/TNG r/TNOmod r/ToastersGW r/Toastmasters r/TodayIAte r/todayifuckedup r/todoist r/toiletviews r/toledo r/TolkienArt r/toloveru r/TomAndJerryMemes r/tombprospectors r/tomhiddleston r/TomSka r/TongueOutHounds r/tonsilstones r/ToobAmps r/tookyoulongenough r/toomanypillows r/toontownrewritten r/TopChef r/topl r/Torchwood r/tornado r/torontoJobs r/torties r/tortoise r/TotalWarArena r/touchfluffytail r/TOUHOUMUSIC r/tourdefrance r/toycameras r/toyexchange r/toys r/TQDC r/TR8R r/Trackballs r/Trackdays r/TrackGirls r/tractors r/tradclimbing r/TRADE r/tradfri r/Traeger r/traingifs r/Trainwreckstv r/transcribe r/transfashionadvice r/transitiongoals r/translation r/TranslationStudies r/Transmatfiring r/TransportFever r/TransSupport r/TransyTalk r/trashyladyboners r/Travala r/Travel_Guide r/travelphotos r/treecipes r/treemovies r/treon r/TrialsGames r/Triangl r/trichotillomania r/Trichsters r/Tricking r/Tripio r/triplej r/trippingthroughtime r/tripreports r/trivia r/TrollAnxiety r/trollbi r/trollfitness r/trollingforababy r/TrollXFitness r/TrollXGirlGamers r/TrollXOver30 r/TrollXWeddings r/Trombone r/tron r/Tropical r/troubledteens r/troutfishing r/TroveCreations r/trpgame r/TrueCinematography r/truecreepyPMs r/TrueCrimeGarage r/truedocumentaries r/truelesbians r/truenews r/TrueNorthPictures r/TruePokemon r/Trumpgrets r/TrumpNicknames r/TrumpRoasts r/trumptweets r/TRXTrading r/TryndamereMains r/TryNotToLaughYouLose r/TRYONBIKINI r/tryonhaul r/TShirt r/ttcafterloss r/tubetop r/tuesday r/TumblrPls r/TuringNet r/Turntablists r/turtles r/turtleswithjobs r/tvtropes r/TVZionApp r/TweakBounty r/TweakBoxApp r/twerknsfw r/twicememes r/twilightimperium r/twintails r/TwitchMains r/twitchstreams r/twitter_memes r/TwoPointHospital r/TwoXADHD r/TWRP r/tyingherhairup r/typemoon r/typewriters r/TyrannyGame r/tzuyu",
            "user_reports": [],
            "saved": false,
            "mod_reason_title": null,
            "gilded": 0,
            "clicked": false,
            "title": "R-T 5k-10k",
            "link_flair_richtext": [],
            "subreddit_name_prefixed": "u/j259awesome",
            "hidden": false,
            "pwls": null,
            "link_flair_css_class": null,
            "downs": 0,
            "thumbnail_height": null,
            "top_awarded_type": null,
            "parent_whitelist_status": null,
            "hide_score": false,
            "name": "t3_csc7hs",
            "quarantine": false,
            "link_flair_text_color": "dark",
            "upvote_ratio": 0.67,
            "author_flair_background_color": null,
            "subreddit_type": "user",
            "ups": 2,
            "total_awards_received": 0,
            "media_embed": {},
            "thumbnail_width": null,
            "author_flair_template_id": null,
            "is_original_content": false,
            "author_fullname": "t2_trtj0",
            "secure_media": null,
            "is_reddit_media_domain": false,
            "is_meta": false,
            "category": null,
            "secure_media_embed": {},
            "link_flair_text": null,
            "can_mod_post": false,
            "score": 2,
            "approved_by": null,
            "is_created_from_ads_ui": false,
            "author_premium": false,
            "thumbnail": "self",
            "edited": false,
            "author_flair_css_class": null,
            "author_flair_richtext": [],
            "gildings": {},
            "content_categories": null,
            "is_self": true,
            "mod_note": null,
            "created": 1566189384.0,
            "link_flair_type": "text",
            "wls": null,
            "removed_by_category": null,
            "banned_by": null,
            "author_flair_type": "text",
            "domain": "self.j259awesome",
            "allow_live_comments": true,
            "selftext_html": "&lt;!-- SC_OFF --&gt;&lt;div class=\"md\"&gt;&lt;p&gt;&lt;a href=\"/r/r4rDFW\"&gt;r/r4rDFW&lt;/a&gt; &lt;a href=\"/r/r4rMelbourne\"&gt;r/r4rMelbourne&lt;/a&gt; &lt;a href=\"/r/r4rSeattle\"&gt;r/r4rSeattle&lt;/a&gt; &lt;a href=\"/r/R6SiegeFashionAdvice\"&gt;r/R6SiegeFashionAdvice&lt;/a&gt; &lt;a href=\"/r/raccoongifs\"&gt;r/raccoongifs&lt;/a&gt; &lt;a href=\"/r/racequeens\"&gt;r/racequeens&lt;/a&gt; &lt;a href=\"/r/RaceTrackDesigns\"&gt;r/RaceTrackDesigns&lt;/a&gt; &lt;a href=\"/r/Rachelbushfans\"&gt;r/Rachelbushfans&lt;/a&gt; &lt;a href=\"/r/RachelMcAdams\"&gt;r/RachelMcAdams&lt;/a&gt; &lt;a href=\"/r/racing\"&gt;r/racing&lt;/a&gt; &lt;a href=\"/r/racistpassdenied\"&gt;r/racistpassdenied&lt;/a&gt; &lt;a href=\"/r/radicalqueers\"&gt;r/radicalqueers&lt;/a&gt; &lt;a href=\"/r/Radiolab\"&gt;r/Radiolab&lt;/a&gt; &lt;a href=\"/r/ragdolls\"&gt;r/ragdolls&lt;/a&gt; &lt;a href=\"/r/RagenChastain\"&gt;r/RagenChastain&lt;/a&gt; &lt;a href=\"/r/RagnarokMEternalLove\"&gt;r/RagnarokMEternalLove&lt;/a&gt; &lt;a href=\"/r/RagnarokOnline\"&gt;r/RagnarokOnline&lt;/a&gt; &lt;a href=\"/r/RaIn\"&gt;r/RaIn&lt;/a&gt; &lt;a href=\"/r/Rainbow6Siege\"&gt;r/Rainbow6Siege&lt;/a&gt; &lt;a href=\"/r/RainbowSix\"&gt;r/RainbowSix&lt;/a&gt; &lt;a href=\"/r/RaiTrade\"&gt;r/RaiTrade&lt;/a&gt; &lt;a href=\"/r/RakanMains\"&gt;r/RakanMains&lt;/a&gt; &lt;a href=\"/r/RallyPorn\"&gt;r/RallyPorn&lt;/a&gt; &lt;a href=\"/r/ralphthemoviemaker\"&gt;r/ralphthemoviemaker&lt;/a&gt; &lt;a href=\"/r/ralsei\"&gt;r/ralsei&lt;/a&gt; &lt;a href=\"/r/ram_trucks\"&gt;r/ram_trucks&lt;/a&gt; &lt;a href=\"/r/RamblersDen\"&gt;r/RamblersDen&lt;/a&gt; &lt;a href=\"/r/randomactsofamazon\"&gt;r/randomactsofamazon&lt;/a&gt; &lt;a href=\"/r/RandomActsOfBras\"&gt;r/RandomActsOfBras&lt;/a&gt; &lt;a href=\"/r/RandomActsOfPegging\"&gt;r/RandomActsOfPegging&lt;/a&gt; &lt;a href=\"/r/RandomActsOfPolish\"&gt;r/RandomActsOfPolish&lt;/a&gt; &lt;a href=\"/r/RandomActsOfVinyl\"&gt;r/RandomActsOfVinyl&lt;/a&gt; &lt;a href=\"/r/randpaul\"&gt;r/randpaul&lt;/a&gt; &lt;a href=\"/r/rangersfc\"&gt;r/rangersfc&lt;/a&gt; &lt;a href=\"/r/RangersOfOblivionGTA\"&gt;r/RangersOfOblivionGTA&lt;/a&gt; &lt;a href=\"/r/rantgrumps\"&gt;r/rantgrumps&lt;/a&gt; &lt;a href=\"/r/Raphtalia\"&gt;r/Raphtalia&lt;/a&gt; &lt;a href=\"/r/RapMoreLikeCrap\"&gt;r/RapMoreLikeCrap&lt;/a&gt; &lt;a href=\"/r/rarelobsters\"&gt;r/rarelobsters&lt;/a&gt; &lt;a href=\"/r/Rarethreats\"&gt;r/Rarethreats&lt;/a&gt; &lt;a href=\"/r/RashidaJones\"&gt;r/RashidaJones&lt;/a&gt; &lt;a href=\"/r/raspberryDIY\"&gt;r/raspberryDIY&lt;/a&gt; &lt;a href=\"/r/RatchetAndClank\"&gt;r/RatchetAndClank&lt;/a&gt; &lt;a href=\"/r/Rate3\"&gt;r/Rate3&lt;/a&gt; &lt;a href=\"/r/RateMyAudio\"&gt;r/RateMyAudio&lt;/a&gt; &lt;a href=\"/r/RateMyButt\"&gt;r/RateMyButt&lt;/a&gt; &lt;a href=\"/r/RatRod\"&gt;r/RatRod&lt;/a&gt; &lt;a href=\"/r/Ravencoin\"&gt;r/Ravencoin&lt;/a&gt; &lt;a href=\"/r/raw\"&gt;r/raw&lt;/a&gt; &lt;a href=\"/r/RayDonovan\"&gt;r/RayDonovan&lt;/a&gt; &lt;a href=\"/r/RayHoltMemes\"&gt;r/RayHoltMemes&lt;/a&gt; &lt;a href=\"/r/razorbacks\"&gt;r/razorbacks&lt;/a&gt; &lt;a href=\"/r/RBNLifeSkills\"&gt;r/RBNLifeSkills&lt;/a&gt; &lt;a href=\"/r/RDR2mysteries\"&gt;r/RDR2mysteries&lt;/a&gt; &lt;a href=\"/r/readitnow\"&gt;r/readitnow&lt;/a&gt; &lt;a href=\"/r/ReadMyScript\"&gt;r/ReadMyScript&lt;/a&gt; &lt;a href=\"/r/ReagentTesting\"&gt;r/ReagentTesting&lt;/a&gt; &lt;a href=\"/r/Real_Estate\"&gt;r/Real_Estate&lt;/a&gt; &lt;a href=\"/r/RealEstatePhotography\"&gt;r/RealEstatePhotography&lt;/a&gt; &lt;a href=\"/r/RealEstateTechnology\"&gt;r/RealEstateTechnology&lt;/a&gt; &lt;a href=\"/r/realhousewives\"&gt;r/realhousewives&lt;/a&gt; &lt;a href=\"/r/RealLifePokemon\"&gt;r/RealLifePokemon&lt;/a&gt; &lt;a href=\"/r/realms\"&gt;r/realms&lt;/a&gt; &lt;a href=\"/r/realsocialengineering\"&gt;r/realsocialengineering&lt;/a&gt; &lt;a href=\"/r/RealTesla\"&gt;r/RealTesla&lt;/a&gt; &lt;a href=\"/r/reasoners\"&gt;r/reasoners&lt;/a&gt; &lt;a href=\"/r/RebelTaxi\"&gt;r/RebelTaxi&lt;/a&gt; &lt;a href=\"/r/REBL\"&gt;r/REBL&lt;/a&gt; &lt;a href=\"/r/recipeclub\"&gt;r/recipeclub&lt;/a&gt; &lt;a href=\"/r/reclassified\"&gt;r/reclassified&lt;/a&gt; &lt;a href=\"/r/recoilbutts\"&gt;r/recoilbutts&lt;/a&gt; &lt;a href=\"/r/recordstore\"&gt;r/recordstore&lt;/a&gt; &lt;a href=\"/r/recovery\"&gt;r/recovery&lt;/a&gt; &lt;a href=\"/r/RecPics\"&gt;r/RecPics&lt;/a&gt; &lt;a href=\"/r/RecRoom\"&gt;r/RecRoom&lt;/a&gt; &lt;a href=\"/r/recycling\"&gt;r/recycling&lt;/a&gt; &lt;a href=\"/r/Red_Dead_Redemption_2\"&gt;r/Red_Dead_Redemption_2&lt;/a&gt; &lt;a href=\"/r/redacted\"&gt;r/redacted&lt;/a&gt; &lt;a href=\"/r/RedactedCharts\"&gt;r/RedactedCharts&lt;/a&gt; &lt;a href=\"/r/ReddHub\"&gt;r/ReddHub&lt;/a&gt; &lt;a href=\"/r/RedditAndChill\"&gt;r/RedditAndChill&lt;/a&gt; &lt;a href=\"/r/RedditArmie\"&gt;r/RedditArmie&lt;/a&gt; &lt;a href=\"/r/RedditCensors\"&gt;r/RedditCensors&lt;/a&gt; &lt;a href=\"/r/RedditDads\"&gt;r/RedditDads&lt;/a&gt; &lt;a href=\"/r/redditguides\"&gt;r/redditguides&lt;/a&gt; &lt;a href=\"/r/RedditInsider\"&gt;r/RedditInsider&lt;/a&gt; &lt;a href=\"/r/redditisland\"&gt;r/redditisland&lt;/a&gt; &lt;a href=\"/r/redditlists\"&gt;r/redditlists&lt;/a&gt; &lt;a href=\"/r/RedditMinusMods\"&gt;r/RedditMinusMods&lt;/a&gt; &lt;a href=\"/r/redditoroftheday\"&gt;r/redditoroftheday&lt;/a&gt; &lt;a href=\"/r/redditstories\"&gt;r/redditstories&lt;/a&gt; &lt;a href=\"/r/RedditVN\"&gt;r/RedditVN&lt;/a&gt; &lt;a href=\"/r/redneckfixes\"&gt;r/redneckfixes&lt;/a&gt; &lt;a href=\"/r/RedneckGifs\"&gt;r/RedneckGifs&lt;/a&gt; &lt;a href=\"/r/redpill\"&gt;r/redpill&lt;/a&gt; &lt;a href=\"/r/redpillbooks\"&gt;r/redpillbooks&lt;/a&gt; &lt;a href=\"/r/RedPillWives\"&gt;r/RedPillWives&lt;/a&gt; &lt;a href=\"/r/RedPulseToken\"&gt;r/RedPulseToken&lt;/a&gt; &lt;a href=\"/r/redrising\"&gt;r/redrising&lt;/a&gt; &lt;a href=\"/r/RedSoccer_EPL\"&gt;r/RedSoccer_EPL&lt;/a&gt; &lt;a href=\"/r/Reduction\"&gt;r/Reduction&lt;/a&gt; &lt;a href=\"/r/RedvolutionOfficial\"&gt;r/RedvolutionOfficial&lt;/a&gt; &lt;a href=\"/r/RedWingShoes\"&gt;r/RedWingShoes&lt;/a&gt; &lt;a href=\"/r/REEEEEE\"&gt;r/REEEEEE&lt;/a&gt; &lt;a href=\"/r/Referrals\"&gt;r/Referrals&lt;/a&gt; &lt;a href=\"/r/regina\"&gt;r/regina&lt;/a&gt; &lt;a href=\"/r/reiki\"&gt;r/reiki&lt;/a&gt; &lt;a href=\"/r/Reincarnation\"&gt;r/Reincarnation&lt;/a&gt; &lt;a href=\"/r/reinforcementlearning\"&gt;r/reinforcementlearning&lt;/a&gt; &lt;a href=\"/r/RelationshipMemes\"&gt;r/RelationshipMemes&lt;/a&gt; &lt;a href=\"/r/RelationshipsOver35\"&gt;r/RelationshipsOver35&lt;/a&gt; &lt;a href=\"/r/Relax\"&gt;r/Relax&lt;/a&gt; &lt;a href=\"/r/relaxedpokemontrades\"&gt;r/relaxedpokemontrades&lt;/a&gt; &lt;a href=\"/r/RelevantXKCD\"&gt;r/RelevantXKCD&lt;/a&gt; &lt;a href=\"/r/REMath\"&gt;r/REMath&lt;/a&gt; &lt;a href=\"/r/ReneeMurden\"&gt;r/ReneeMurden&lt;/a&gt; &lt;a href=\"/r/RenektonMains\"&gt;r/RenektonMains&lt;/a&gt; &lt;a href=\"/r/renfaire\"&gt;r/renfaire&lt;/a&gt; &lt;a href=\"/r/Reno\"&gt;r/Reno&lt;/a&gt; &lt;a href=\"/r/Rento\"&gt;r/Rento&lt;/a&gt; &lt;a href=\"/r/RepGuides\"&gt;r/RepGuides&lt;/a&gt; &lt;a href=\"/r/RepLadiesBST\"&gt;r/RepLadiesBST&lt;/a&gt; &lt;a href=\"/r/reptiliandude\"&gt;r/reptiliandude&lt;/a&gt; &lt;a href=\"/r/republicans\"&gt;r/republicans&lt;/a&gt; &lt;a href=\"/r/resilientcommunities\"&gt;r/resilientcommunities&lt;/a&gt; &lt;a href=\"/r/ResinCasting\"&gt;r/ResinCasting&lt;/a&gt; &lt;a href=\"/r/resonatingfury\"&gt;r/resonatingfury&lt;/a&gt; &lt;a href=\"/r/ResponsibleRevenge\"&gt;r/ResponsibleRevenge&lt;/a&gt; &lt;a href=\"/r/RestaurantsThatMeme\"&gt;r/RestaurantsThatMeme&lt;/a&gt; &lt;a href=\"/r/restaurateur\"&gt;r/restaurateur&lt;/a&gt; &lt;a href=\"/r/Resume\"&gt;r/Resume&lt;/a&gt; &lt;a href=\"/r/retailhell\"&gt;r/retailhell&lt;/a&gt; &lt;a href=\"/r/retailporn\"&gt;r/retailporn&lt;/a&gt; &lt;a href=\"/r/retardsinaction\"&gt;r/retardsinaction&lt;/a&gt; &lt;a href=\"/r/retiredusername\"&gt;r/retiredusername&lt;/a&gt; &lt;a href=\"/r/retorted\"&gt;r/retorted&lt;/a&gt; &lt;a href=\"/r/RetroArch\"&gt;r/RetroArch&lt;/a&gt; &lt;a href=\"/r/RetroGamePorn\"&gt;r/RetroGamePorn&lt;/a&gt; &lt;a href=\"/r/retrogameswap\"&gt;r/retrogameswap&lt;/a&gt; &lt;a href=\"/r/RetroLibraryMusic\"&gt;r/RetroLibraryMusic&lt;/a&gt; &lt;a href=\"/r/Revit\"&gt;r/Revit&lt;/a&gt; &lt;a href=\"/r/Revolvers\"&gt;r/Revolvers&lt;/a&gt; &lt;a href=\"/r/RevueStarlight\"&gt;r/RevueStarlight&lt;/a&gt; &lt;a href=\"/r/rfelectronics\"&gt;r/rfelectronics&lt;/a&gt; &lt;a href=\"/r/rheumatoid\"&gt;r/rheumatoid&lt;/a&gt; &lt;a href=\"/r/rhps\"&gt;r/rhps&lt;/a&gt; &lt;a href=\"/r/RicardoMilosMemes\"&gt;r/RicardoMilosMemes&lt;/a&gt; &lt;a href=\"/r/RiCare\"&gt;r/RiCare&lt;/a&gt; &lt;a href=\"/r/RiceCookerRecipes\"&gt;r/RiceCookerRecipes&lt;/a&gt; &lt;a href=\"/r/rickandmorty_C137\"&gt;r/rickandmorty_C137&lt;/a&gt; &lt;a href=\"/r/rickandmortyGIFs\"&gt;r/rickandmortyGIFs&lt;/a&gt; &lt;a href=\"/r/Rickyisms\"&gt;r/Rickyisms&lt;/a&gt; &lt;a href=\"/r/riddim\"&gt;r/riddim&lt;/a&gt; &lt;a href=\"/r/Rifftrax\"&gt;r/Rifftrax&lt;/a&gt; &lt;a href=\"/r/Rift\"&gt;r/Rift&lt;/a&gt; &lt;a href=\"/r/RightwingLGBT\"&gt;r/RightwingLGBT&lt;/a&gt; &lt;a href=\"/r/RimWorldSeeds\"&gt;r/RimWorldSeeds&lt;/a&gt; &lt;a href=\"/r/Ring\"&gt;r/Ring&lt;/a&gt; &lt;a href=\"/r/ringdoorbell\"&gt;r/ringdoorbell&lt;/a&gt; &lt;a href=\"/r/ripplers\"&gt;r/ripplers&lt;/a&gt; &lt;a href=\"/r/RippleTalk\"&gt;r/RippleTalk&lt;/a&gt; &lt;a href=\"/r/risa\"&gt;r/risa&lt;/a&gt; &lt;a href=\"/r/riseagainst\"&gt;r/riseagainst&lt;/a&gt; &lt;a href=\"/r/RiseofCivilizationsEn\"&gt;r/RiseofCivilizationsEn&lt;/a&gt; &lt;a href=\"/r/RiseofKingdoms\"&gt;r/RiseofKingdoms&lt;/a&gt; &lt;a href=\"/r/riskyclick\"&gt;r/riskyclick&lt;/a&gt; &lt;a href=\"/r/riskyclickoftheday\"&gt;r/riskyclickoftheday&lt;/a&gt; &lt;a href=\"/r/RLCustomTraining\"&gt;r/RLCustomTraining&lt;/a&gt; &lt;a href=\"/r/RnBHeads\"&gt;r/RnBHeads&lt;/a&gt; &lt;a href=\"/r/RoadPorn\"&gt;r/RoadPorn&lt;/a&gt; &lt;a href=\"/r/roastmytrack\"&gt;r/roastmytrack&lt;/a&gt; &lt;a href=\"/r/robac\"&gt;r/robac&lt;/a&gt; &lt;a href=\"/r/Robbaz\"&gt;r/Robbaz&lt;/a&gt; &lt;a href=\"/r/robinhobb\"&gt;r/robinhobb&lt;/a&gt; &lt;a href=\"/r/robloxgamedev\"&gt;r/robloxgamedev&lt;/a&gt; &lt;a href=\"/r/Robocraft\"&gt;r/Robocraft&lt;/a&gt; &lt;a href=\"/r/robots\"&gt;r/robots&lt;/a&gt; &lt;a href=\"/r/rockabilly\"&gt;r/rockabilly&lt;/a&gt; &lt;a href=\"/r/RockClimbing\"&gt;r/RockClimbing&lt;/a&gt; &lt;a href=\"/r/RocketLab\"&gt;r/RocketLab&lt;/a&gt; &lt;a href=\"/r/RodSquare\"&gt;r/RodSquare&lt;/a&gt; &lt;a href=\"/r/ROH\"&gt;r/ROH&lt;/a&gt; &lt;a href=\"/r/rojava\"&gt;r/rojava&lt;/a&gt; &lt;a href=\"/r/roll20LFG\"&gt;r/roll20LFG&lt;/a&gt; &lt;a href=\"/r/rome\"&gt;r/rome&lt;/a&gt; &lt;a href=\"/r/romemes\"&gt;r/romemes&lt;/a&gt; &lt;a href=\"/r/ronswanson\"&gt;r/ronswanson&lt;/a&gt; &lt;a href=\"/r/roomdetective\"&gt;r/roomdetective&lt;/a&gt; &lt;a href=\"/r/rootkit\"&gt;r/rootkit&lt;/a&gt; &lt;a href=\"/r/ror2\"&gt;r/ror2&lt;/a&gt; &lt;a href=\"/r/Rosacea\"&gt;r/Rosacea&lt;/a&gt; &lt;a href=\"/r/ROTC\"&gt;r/ROTC&lt;/a&gt; &lt;a href=\"/r/RothWellden\"&gt;r/RothWellden&lt;/a&gt; &lt;a href=\"/r/rotmgtradingpost\"&gt;r/rotmgtradingpost&lt;/a&gt; &lt;a href=\"/r/RowlingWritings\"&gt;r/RowlingWritings&lt;/a&gt; &lt;a href=\"/r/rpdrgonewild\"&gt;r/rpdrgonewild&lt;/a&gt; &lt;a href=\"/r/RPGhumor\"&gt;r/RPGhumor&lt;/a&gt; &lt;a href=\"/r/RPI\"&gt;r/RPI&lt;/a&gt; &lt;a href=\"/r/RS3Ironmen\"&gt;r/RS3Ironmen&lt;/a&gt; &lt;a href=\"/r/RStudio\"&gt;r/RStudio&lt;/a&gt; &lt;a href=\"/r/ru\"&gt;r/ru&lt;/a&gt; &lt;a href=\"/r/rugby\"&gt;r/rugby&lt;/a&gt; &lt;a href=\"/r/rugbystreams\"&gt;r/rugbystreams&lt;/a&gt; &lt;a href=\"/r/ruger\"&gt;r/ruger&lt;/a&gt; &lt;a href=\"/r/Rule34FanArt\"&gt;r/Rule34FanArt&lt;/a&gt; &lt;a href=\"/r/Rule34SFM\"&gt;r/Rule34SFM&lt;/a&gt; &lt;a href=\"/r/rule63\"&gt;r/rule63&lt;/a&gt; &lt;a href=\"/r/rulesofsurvival\"&gt;r/rulesofsurvival&lt;/a&gt; &lt;a href=\"/r/Runner5\"&gt;r/Runner5&lt;/a&gt; &lt;a href=\"/r/RunnerHub\"&gt;r/RunnerHub&lt;/a&gt; &lt;a href=\"/r/runninglifestyle\"&gt;r/runninglifestyle&lt;/a&gt; &lt;a href=\"/r/runthejewels\"&gt;r/runthejewels&lt;/a&gt; &lt;a href=\"/r/rupaulsdragracedrama\"&gt;r/rupaulsdragracedrama&lt;/a&gt; &lt;a href=\"/r/RussiaDenies\"&gt;r/RussiaDenies&lt;/a&gt; &lt;a href=\"/r/RussianDoll\"&gt;r/RussianDoll&lt;/a&gt; &lt;a href=\"/r/rust_gamedev\"&gt;r/rust_gamedev&lt;/a&gt; &lt;a href=\"/r/RVLiving\"&gt;r/RVLiving&lt;/a&gt; &lt;a href=\"/r/RX7\"&gt;r/RX7&lt;/a&gt; &lt;a href=\"/r/ryerson\"&gt;r/ryerson&lt;/a&gt; &lt;a href=\"/r/RyzeMains\"&gt;r/RyzeMains&lt;/a&gt; &lt;/p&gt;\n\n&lt;p&gt;&amp;#x200B;&lt;/p&gt;\n\n&lt;p&gt;&lt;a href=\"/r/S01E01\"&gt;r/S01E01&lt;/a&gt; &lt;a href=\"/r/S2000\"&gt;r/S2000&lt;/a&gt; &lt;a href=\"/r/saab\"&gt;r/saab&lt;/a&gt; &lt;a href=\"/r/SaaS\"&gt;r/SaaS&lt;/a&gt; &lt;a href=\"/r/Sabermetrics\"&gt;r/Sabermetrics&lt;/a&gt; &lt;a href=\"/r/sabrina\"&gt;r/sabrina&lt;/a&gt; &lt;a href=\"/r/SabrinaCarpenter\"&gt;r/SabrinaCarpenter&lt;/a&gt; &lt;a href=\"/r/sadbuddyretard\"&gt;r/sadbuddyretard&lt;/a&gt; &lt;a href=\"/r/SaddestBackflip\"&gt;r/SaddestBackflip&lt;/a&gt; &lt;a href=\"/r/SAGAcomic\"&gt;r/SAGAcomic&lt;/a&gt; &lt;a href=\"/r/SAHP\"&gt;r/SAHP&lt;/a&gt; &lt;a href=\"/r/SailboatCruising\"&gt;r/SailboatCruising&lt;/a&gt; &lt;a href=\"/r/sailingcrew\"&gt;r/sailingcrew&lt;/a&gt; &lt;a href=\"/r/SaintsFC\"&gt;r/SaintsFC&lt;/a&gt; &lt;a href=\"/r/Sakartvelo\"&gt;r/Sakartvelo&lt;/a&gt; &lt;a href=\"/r/saltandsanctuary\"&gt;r/saltandsanctuary&lt;/a&gt; &lt;a href=\"/r/saltyobituaries\"&gt;r/saltyobituaries&lt;/a&gt; &lt;a href=\"/r/Salvia\"&gt;r/Salvia&lt;/a&gt; &lt;a href=\"/r/SamandTolki\"&gt;r/SamandTolki&lt;/a&gt; &lt;a href=\"/r/SamPepper\"&gt;r/SamPepper&lt;/a&gt; &lt;a href=\"/r/Samplehunters\"&gt;r/Samplehunters&lt;/a&gt; &lt;a href=\"/r/SamuraiChamploo\"&gt;r/SamuraiChamploo&lt;/a&gt; &lt;a href=\"/r/Sandman\"&gt;r/Sandman&lt;/a&gt; &lt;a href=\"/r/Sandwiches\"&gt;r/Sandwiches&lt;/a&gt; &lt;a href=\"/r/SantaBarbara\"&gt;r/SantaBarbara&lt;/a&gt; &lt;a href=\"/r/santaclaritadiet\"&gt;r/santaclaritadiet&lt;/a&gt; &lt;a href=\"/r/santacruz\"&gt;r/santacruz&lt;/a&gt; &lt;a href=\"/r/santashelpers\"&gt;r/santashelpers&lt;/a&gt; &lt;a href=\"/r/SaoirseRonan\"&gt;r/SaoirseRonan&lt;/a&gt; &lt;a href=\"/r/SAP\"&gt;r/SAP&lt;/a&gt; &lt;a href=\"/r/SapphoAndHerFriend\"&gt;r/SapphoAndHerFriend&lt;/a&gt; &lt;a href=\"/r/saraba1st\"&gt;r/saraba1st&lt;/a&gt; &lt;a href=\"/r/SarahChalke\"&gt;r/SarahChalke&lt;/a&gt; &lt;a href=\"/r/SarahSnyder\"&gt;r/SarahSnyder&lt;/a&gt; &lt;a href=\"/r/SarahStephens\"&gt;r/SarahStephens&lt;/a&gt; &lt;a href=\"/r/SaraMeiKasaiOfficial\"&gt;r/SaraMeiKasaiOfficial&lt;/a&gt; &lt;a href=\"/r/SaraMillsSecret\"&gt;r/SaraMillsSecret&lt;/a&gt; &lt;a href=\"/r/sarcasm\"&gt;r/sarcasm&lt;/a&gt; &lt;a href=\"/r/Satan\"&gt;r/Satan&lt;/a&gt; &lt;a href=\"/r/satania\"&gt;r/satania&lt;/a&gt; &lt;a href=\"/r/satire\"&gt;r/satire&lt;/a&gt; &lt;a href=\"/r/satisfyinggrass\"&gt;r/satisfyinggrass&lt;/a&gt; &lt;a href=\"/r/saudelobaes\"&gt;r/saudelobaes&lt;/a&gt; &lt;a href=\"/r/Savage_Memes\"&gt;r/Savage_Memes&lt;/a&gt; &lt;a href=\"/r/SavageOuija\"&gt;r/SavageOuija&lt;/a&gt; &lt;a href=\"/r/savageworlds\"&gt;r/savageworlds&lt;/a&gt; &lt;a href=\"/r/savannah\"&gt;r/savannah&lt;/a&gt; &lt;a href=\"/r/saxophone\"&gt;r/saxophone&lt;/a&gt; &lt;a href=\"/r/SayHenloToMyLilFren\"&gt;r/SayHenloToMyLilFren&lt;/a&gt; &lt;a href=\"/r/SBU\"&gt;r/SBU&lt;/a&gt; &lt;a href=\"/r/sca\"&gt;r/sca&lt;/a&gt; &lt;a href=\"/r/scacjdiscussion\"&gt;r/scacjdiscussion&lt;/a&gt; &lt;a href=\"/r/scamslayers\"&gt;r/scamslayers&lt;/a&gt; &lt;a href=\"/r/Scandal\"&gt;r/Scandal&lt;/a&gt; &lt;a href=\"/r/ScaringChildren\"&gt;r/ScaringChildren&lt;/a&gt; &lt;a href=\"/r/Scarrapics\"&gt;r/Scarrapics&lt;/a&gt; &lt;a href=\"/r/SCBuildIt\"&gt;r/SCBuildIt&lt;/a&gt; &lt;a href=\"/r/scenes\"&gt;r/scenes&lt;/a&gt; &lt;a href=\"/r/scheme\"&gt;r/scheme&lt;/a&gt; &lt;a href=\"/r/SchittsCreek\"&gt;r/SchittsCreek&lt;/a&gt; &lt;a href=\"/r/Schizoid\"&gt;r/Schizoid&lt;/a&gt; &lt;a href=\"/r/SCHLAND\"&gt;r/SCHLAND&lt;/a&gt; &lt;a href=\"/r/schnauzers\"&gt;r/schnauzers&lt;/a&gt; &lt;a href=\"/r/schrutetoobig\"&gt;r/schrutetoobig&lt;/a&gt; &lt;a href=\"/r/schweiz\"&gt;r/schweiz&lt;/a&gt; &lt;a href=\"/r/science2\"&gt;r/science2&lt;/a&gt; &lt;a href=\"/r/ScienceGIFs\"&gt;r/ScienceGIFs&lt;/a&gt; &lt;a href=\"/r/ScienceNetwork\"&gt;r/ScienceNetwork&lt;/a&gt; &lt;a href=\"/r/ScienceParents\"&gt;r/ScienceParents&lt;/a&gt; &lt;a href=\"/r/scientificresearch\"&gt;r/scientificresearch&lt;/a&gt; &lt;a href=\"/r/ScientistsMarch\"&gt;r/ScientistsMarch&lt;/a&gt; &lt;a href=\"/r/Scientits\"&gt;r/Scientits&lt;/a&gt; &lt;a href=\"/r/scifi_bookclub\"&gt;r/scifi_bookclub&lt;/a&gt; &lt;a href=\"/r/SciFiConcepts\"&gt;r/SciFiConcepts&lt;/a&gt; &lt;a href=\"/r/SciFiModels\"&gt;r/SciFiModels&lt;/a&gt; &lt;a href=\"/r/SCJerk\"&gt;r/SCJerk&lt;/a&gt; &lt;a href=\"/r/Scoobydoo\"&gt;r/Scoobydoo&lt;/a&gt; &lt;a href=\"/r/scoreball\"&gt;r/scoreball&lt;/a&gt; &lt;a href=\"/r/ScottishFootball\"&gt;r/ScottishFootball&lt;/a&gt; &lt;a href=\"/r/scotus\"&gt;r/scotus&lt;/a&gt; &lt;a href=\"/r/SCPSecretLab\"&gt;r/SCPSecretLab&lt;/a&gt; &lt;a href=\"/r/ScratchyScratchy\"&gt;r/ScratchyScratchy&lt;/a&gt; &lt;a href=\"/r/ScreamQueensTV\"&gt;r/ScreamQueensTV&lt;/a&gt; &lt;a href=\"/r/ScreenCapsForTheSoul\"&gt;r/ScreenCapsForTheSoul&lt;/a&gt; &lt;a href=\"/r/scripteddoggifs\"&gt;r/scripteddoggifs&lt;/a&gt; &lt;a href=\"/r/ScriptSwap\"&gt;r/ScriptSwap&lt;/a&gt; &lt;a href=\"/r/scrum\"&gt;r/scrum&lt;/a&gt; &lt;a href=\"/r/Sdorica\"&gt;r/Sdorica&lt;/a&gt; &lt;a href=\"/r/seaofgreed\"&gt;r/seaofgreed&lt;/a&gt; &lt;a href=\"/r/searchandrescue\"&gt;r/searchandrescue&lt;/a&gt; &lt;a href=\"/r/secondlife\"&gt;r/secondlife&lt;/a&gt; &lt;a href=\"/r/SecondWorldProblems\"&gt;r/SecondWorldProblems&lt;/a&gt; &lt;a href=\"/r/SecretSubreddit\"&gt;r/SecretSubreddit&lt;/a&gt; &lt;a href=\"/r/SecretWorldLegends\"&gt;r/SecretWorldLegends&lt;/a&gt; &lt;a href=\"/r/secularbuddhism\"&gt;r/secularbuddhism&lt;/a&gt; &lt;a href=\"/r/securityguards\"&gt;r/securityguards&lt;/a&gt; &lt;a href=\"/r/seedstock\"&gt;r/seedstock&lt;/a&gt; &lt;a href=\"/r/seedswap\"&gt;r/seedswap&lt;/a&gt; &lt;a href=\"/r/seekingsisterwifetlc\"&gt;r/seekingsisterwifetlc&lt;/a&gt; &lt;a href=\"/r/Seethroughyogapants\"&gt;r/Seethroughyogapants&lt;/a&gt; &lt;a href=\"/r/SEGA\"&gt;r/SEGA&lt;/a&gt; &lt;a href=\"/r/SEGAGENESIS\"&gt;r/SEGAGENESIS&lt;/a&gt; &lt;a href=\"/r/SegaSaturn\"&gt;r/SegaSaturn&lt;/a&gt; &lt;a href=\"/r/seiyuu\"&gt;r/seiyuu&lt;/a&gt; &lt;a href=\"/r/SelenaGomezLust\"&gt;r/SelenaGomezLust&lt;/a&gt; &lt;a href=\"/r/selfeducation\"&gt;r/selfeducation&lt;/a&gt; &lt;a href=\"/r/SelfHarmScars\"&gt;r/SelfHarmScars&lt;/a&gt; &lt;a href=\"/r/Semenretention\"&gt;r/Semenretention&lt;/a&gt; &lt;a href=\"/r/senrankagura\"&gt;r/senrankagura&lt;/a&gt; &lt;a href=\"/r/SEO_Infographics\"&gt;r/SEO_Infographics&lt;/a&gt; &lt;a href=\"/r/seoul\"&gt;r/seoul&lt;/a&gt; &lt;a href=\"/r/Sephora\"&gt;r/Sephora&lt;/a&gt; &lt;a href=\"/r/serial_killers\"&gt;r/serial_killers&lt;/a&gt; &lt;a href=\"/r/serialpodcastorigins\"&gt;r/serialpodcastorigins&lt;/a&gt; &lt;a href=\"/r/seriea\"&gt;r/seriea&lt;/a&gt; &lt;a href=\"/r/SeriousFIFA\"&gt;r/SeriousFIFA&lt;/a&gt; &lt;a href=\"/r/Serverlife\"&gt;r/Serverlife&lt;/a&gt; &lt;a href=\"/r/servers\"&gt;r/servers&lt;/a&gt; &lt;a href=\"/r/service_dogs\"&gt;r/service_dogs&lt;/a&gt; &lt;a href=\"/r/SesameStreetMemes\"&gt;r/SesameStreetMemes&lt;/a&gt; &lt;a href=\"/r/SETI\"&gt;r/SETI&lt;/a&gt; &lt;a href=\"/r/SEUT\"&gt;r/SEUT&lt;/a&gt; &lt;a href=\"/r/sexmemes\"&gt;r/sexmemes&lt;/a&gt; &lt;a href=\"/r/SEXONDRUGS\"&gt;r/SEXONDRUGS&lt;/a&gt; &lt;a href=\"/r/sexpertslounge\"&gt;r/sexpertslounge&lt;/a&gt; &lt;a href=\"/r/sextips\"&gt;r/sextips&lt;/a&gt; &lt;a href=\"/r/SexyCelebFemales\"&gt;r/SexyCelebFemales&lt;/a&gt; &lt;a href=\"/r/sexycelebs\"&gt;r/sexycelebs&lt;/a&gt; &lt;a href=\"/r/sexygames\"&gt;r/sexygames&lt;/a&gt; &lt;a href=\"/r/SexyMusicVideos\"&gt;r/SexyMusicVideos&lt;/a&gt; &lt;a href=\"/r/SF_Book_Club\"&gt;r/SF_Book_Club&lt;/a&gt; &lt;a href=\"/r/SFBayHousing\"&gt;r/SFBayHousing&lt;/a&gt; &lt;a href=\"/r/SFBayJobs\"&gt;r/SFBayJobs&lt;/a&gt; &lt;a href=\"/r/SFWNextDoorGirls\"&gt;r/SFWNextDoorGirls&lt;/a&gt; &lt;a href=\"/r/sfwtrees\"&gt;r/sfwtrees&lt;/a&gt; &lt;a href=\"/r/shacomains\"&gt;r/shacomains&lt;/a&gt; &lt;a href=\"/r/shadow_of_war\"&gt;r/shadow_of_war&lt;/a&gt; &lt;a href=\"/r/ShadowBan\"&gt;r/ShadowBan&lt;/a&gt; &lt;a href=\"/r/shadowhunters\"&gt;r/shadowhunters&lt;/a&gt; &lt;a href=\"/r/ShadowoftheColossus\"&gt;r/ShadowoftheColossus&lt;/a&gt; &lt;a href=\"/r/shadowrunreturns\"&gt;r/shadowrunreturns&lt;/a&gt; &lt;a href=\"/r/ShaileneWoodley\"&gt;r/ShaileneWoodley&lt;/a&gt; &lt;a href=\"/r/shakira\"&gt;r/shakira&lt;/a&gt; &lt;a href=\"/r/shallowhouse\"&gt;r/shallowhouse&lt;/a&gt; &lt;a href=\"/r/shallyzsaa\"&gt;r/shallyzsaa&lt;/a&gt; &lt;a href=\"/r/Shaneisms\"&gt;r/Shaneisms&lt;/a&gt; &lt;a href=\"/r/ShannanWatts\"&gt;r/ShannanWatts&lt;/a&gt; &lt;a href=\"/r/SharePLEX\"&gt;r/SharePLEX&lt;/a&gt; &lt;a href=\"/r/sharkswithhumanteeth\"&gt;r/sharkswithhumanteeth&lt;/a&gt; &lt;a href=\"/r/sharpening\"&gt;r/sharpening&lt;/a&gt; &lt;a href=\"/r/shaving\"&gt;r/shaving&lt;/a&gt; &lt;a href=\"/r/sheetmusic\"&gt;r/sheetmusic&lt;/a&gt; &lt;a href=\"/r/sheffield\"&gt;r/sheffield&lt;/a&gt; &lt;a href=\"/r/ShemaleSexDolls\"&gt;r/ShemaleSexDolls&lt;/a&gt; &lt;a href=\"/r/Shenmue\"&gt;r/Shenmue&lt;/a&gt; &lt;a href=\"/r/ShibaInu\"&gt;r/ShibaInu&lt;/a&gt; &lt;a href=\"/r/Shihtzu\"&gt;r/Shihtzu&lt;/a&gt; &lt;a href=\"/r/shills\"&gt;r/shills&lt;/a&gt; &lt;a href=\"/r/SHINee\"&gt;r/SHINee&lt;/a&gt; &lt;a href=\"/r/ShipwreckPorn\"&gt;r/ShipwreckPorn&lt;/a&gt; &lt;a href=\"/r/ShitGoneWildSays\"&gt;r/ShitGoneWildSays&lt;/a&gt; &lt;a href=\"/r/ShitJadenSays\"&gt;r/ShitJadenSays&lt;/a&gt; &lt;a href=\"/r/ShitJamesSays\"&gt;r/ShitJamesSays&lt;/a&gt; &lt;a href=\"/r/ShitNsSay\"&gt;r/ShitNsSay&lt;/a&gt; &lt;a href=\"/r/shitpostbound\"&gt;r/shitpostbound&lt;/a&gt; &lt;a href=\"/r/shitposting\"&gt;r/shitposting&lt;/a&gt; &lt;a href=\"/r/ShitpostXIV\"&gt;r/ShitpostXIV&lt;/a&gt; &lt;a href=\"/r/ShitRamsaySays\"&gt;r/ShitRamsaySays&lt;/a&gt; &lt;a href=\"/r/ShitRimworldSays\"&gt;r/ShitRimworldSays&lt;/a&gt; &lt;a href=\"/r/ShitThe_DonaldSays\"&gt;r/ShitThe_DonaldSays&lt;/a&gt; &lt;a href=\"/r/shittingadvice\"&gt;r/shittingadvice&lt;/a&gt; &lt;a href=\"/r/shitty_ecr\"&gt;r/shitty_ecr&lt;/a&gt; &lt;a href=\"/r/shitty_housing\"&gt;r/shitty_housing&lt;/a&gt; &lt;a href=\"/r/Shittyaskflying\"&gt;r/Shittyaskflying&lt;/a&gt; &lt;a href=\"/r/ShittyBuildaPC\"&gt;r/ShittyBuildaPC&lt;/a&gt; &lt;a href=\"/r/shittyconspiracy\"&gt;r/shittyconspiracy&lt;/a&gt; &lt;a href=\"/r/shittycoolguides\"&gt;r/shittycoolguides&lt;/a&gt; &lt;a href=\"/r/Shittycosplay\"&gt;r/Shittycosplay&lt;/a&gt; &lt;a href=\"/r/shittydiy\"&gt;r/shittydiy&lt;/a&gt; &lt;a href=\"/r/shittyengineering\"&gt;r/shittyengineering&lt;/a&gt; &lt;a href=\"/r/Shittygamecollecting\"&gt;r/Shittygamecollecting&lt;/a&gt; &lt;a href=\"/r/shittypopanalysis\"&gt;r/shittypopanalysis&lt;/a&gt; &lt;a href=\"/r/ShittySeduction\"&gt;r/ShittySeduction&lt;/a&gt; &lt;a href=\"/r/ShittySekiro\"&gt;r/ShittySekiro&lt;/a&gt; &lt;a href=\"/r/ShittyShittyRainbow6\"&gt;r/ShittyShittyRainbow6&lt;/a&gt; &lt;a href=\"/r/shittyshowerthoughts\"&gt;r/shittyshowerthoughts&lt;/a&gt; &lt;a href=\"/r/shittystockphotos\"&gt;r/shittystockphotos&lt;/a&gt; &lt;a href=\"/r/ShittyTechDeals\"&gt;r/ShittyTechDeals&lt;/a&gt; &lt;a href=\"/r/ShittyWholesomeMemes\"&gt;r/ShittyWholesomeMemes&lt;/a&gt; &lt;a href=\"/r/shittywoodworking\"&gt;r/shittywoodworking&lt;/a&gt; &lt;a href=\"/r/shoebots\"&gt;r/shoebots&lt;/a&gt; &lt;a href=\"/r/Shoes\"&gt;r/Shoes&lt;/a&gt; &lt;a href=\"/r/shooting_stars\"&gt;r/shooting_stars&lt;/a&gt; &lt;a href=\"/r/shootingcars\"&gt;r/shootingcars&lt;/a&gt; &lt;a href=\"/r/shoppingaddiction\"&gt;r/shoppingaddiction&lt;/a&gt; &lt;a href=\"/r/shoptours\"&gt;r/shoptours&lt;/a&gt; &lt;a href=\"/r/shorthorror\"&gt;r/shorthorror&lt;/a&gt; &lt;a href=\"/r/ShortSadStories\"&gt;r/ShortSadStories&lt;/a&gt; &lt;a href=\"/r/shortscifistories\"&gt;r/shortscifistories&lt;/a&gt; &lt;a href=\"/r/shortwave\"&gt;r/shortwave&lt;/a&gt; &lt;a href=\"/r/shortykeepingittight\"&gt;r/shortykeepingittight&lt;/a&gt; &lt;a href=\"/r/ShotaCops\"&gt;r/ShotaCops&lt;/a&gt; &lt;a href=\"/r/shoujoai\"&gt;r/shoujoai&lt;/a&gt; &lt;a href=\"/r/showbox\"&gt;r/showbox&lt;/a&gt; &lt;a href=\"/r/ShowoffsCrashingCars\"&gt;r/ShowoffsCrashingCars&lt;/a&gt; &lt;a href=\"/r/Shrekmemes\"&gt;r/Shrekmemes&lt;/a&gt; &lt;a href=\"/r/Shrimping\"&gt;r/Shrimping&lt;/a&gt; &lt;a href=\"/r/ShrineOfJonesy\"&gt;r/ShrineOfJonesy&lt;/a&gt; &lt;a href=\"/r/ShroomID\"&gt;r/ShroomID&lt;/a&gt; &lt;a href=\"/r/ShrugLifeSyndicate\"&gt;r/ShrugLifeSyndicate&lt;/a&gt; &lt;a href=\"/r/Shuffles_Deck\"&gt;r/Shuffles_Deck&lt;/a&gt; &lt;a href=\"/r/Siamesecats\"&gt;r/Siamesecats&lt;/a&gt; &lt;a href=\"/r/siatrader\"&gt;r/siatrader&lt;/a&gt; &lt;a href=\"/r/sidehustle\"&gt;r/sidehustle&lt;/a&gt; &lt;a href=\"/r/Sidemen\"&gt;r/Sidemen&lt;/a&gt; &lt;a href=\"/r/signal\"&gt;r/signal&lt;/a&gt; &lt;a href=\"/r/Sikh\"&gt;r/Sikh&lt;/a&gt; &lt;a href=\"/r/siliconvalley\"&gt;r/siliconvalley&lt;/a&gt; &lt;a href=\"/r/SilviaCaruso\"&gt;r/SilviaCaruso&lt;/a&gt; &lt;a href=\"/r/simcity4\"&gt;r/simcity4&lt;/a&gt; &lt;a href=\"/r/simonfraser\"&gt;r/simonfraser&lt;/a&gt; &lt;a href=\"/r/simpleios\"&gt;r/simpleios&lt;/a&gt; &lt;a href=\"/r/SimplySporty\"&gt;r/SimplySporty&lt;/a&gt; &lt;a href=\"/r/simpsonswave\"&gt;r/simpsonswave&lt;/a&gt; &lt;a href=\"/r/Sims3\"&gt;r/Sims3&lt;/a&gt; &lt;a href=\"/r/SimsIRL\"&gt;r/SimsIRL&lt;/a&gt; &lt;a href=\"/r/Simulate\"&gt;r/Simulate&lt;/a&gt; &lt;a href=\"/r/SimulationTheory\"&gt;r/SimulationTheory&lt;/a&gt; &lt;a href=\"/r/singedmains\"&gt;r/singedmains&lt;/a&gt; &lt;a href=\"/r/SingleParents\"&gt;r/SingleParents&lt;/a&gt; &lt;a href=\"/r/singlepixelmemes\"&gt;r/singlepixelmemes&lt;/a&gt; &lt;a href=\"/r/Sinkpissers\"&gt;r/Sinkpissers&lt;/a&gt; &lt;a href=\"/r/SinonAssOnline\"&gt;r/SinonAssOnline&lt;/a&gt; &lt;a href=\"/r/SiriFail\"&gt;r/SiriFail&lt;/a&gt; &lt;a href=\"/r/Sissydating\"&gt;r/Sissydating&lt;/a&gt; &lt;a href=\"/r/SISwimsuitGirls\"&gt;r/SISwimsuitGirls&lt;/a&gt; &lt;a href=\"/r/Siv\"&gt;r/Siv&lt;/a&gt; &lt;a href=\"/r/sjain_guides\"&gt;r/sjain_guides&lt;/a&gt; &lt;a href=\"/r/Sjin\"&gt;r/Sjin&lt;/a&gt; &lt;a href=\"/r/SJSU\"&gt;r/SJSU&lt;/a&gt; &lt;a href=\"/r/SJWstories\"&gt;r/SJWstories&lt;/a&gt; &lt;a href=\"/r/skam\"&gt;r/skam&lt;/a&gt; &lt;a href=\"/r/skatespotporn\"&gt;r/skatespotporn&lt;/a&gt; &lt;a href=\"/r/sketchapp\"&gt;r/sketchapp&lt;/a&gt; &lt;a href=\"/r/Sketchup\"&gt;r/Sketchup&lt;/a&gt; &lt;a href=\"/r/ski\"&gt;r/ski&lt;/a&gt; &lt;a href=\"/r/SkinCareScience\"&gt;r/SkinCareScience&lt;/a&gt; &lt;a href=\"/r/skinsTV\"&gt;r/skinsTV&lt;/a&gt; &lt;a href=\"/r/SkyFactory\"&gt;r/SkyFactory&lt;/a&gt; &lt;a href=\"/r/Skyforge\"&gt;r/Skyforge&lt;/a&gt; &lt;a href=\"/r/SkyLine\"&gt;r/SkyLine&lt;/a&gt; &lt;a href=\"/r/skylineporn\"&gt;r/skylineporn&lt;/a&gt; &lt;a href=\"/r/SkyrimBuilds\"&gt;r/SkyrimBuilds&lt;/a&gt; &lt;a href=\"/r/skyrimrequiem\"&gt;r/skyrimrequiem&lt;/a&gt; &lt;a href=\"/r/SkyrimSkills_IRL\"&gt;r/SkyrimSkills_IRL&lt;/a&gt; &lt;a href=\"/r/Slack\"&gt;r/Slack&lt;/a&gt; &lt;a href=\"/r/Slackline\"&gt;r/Slackline&lt;/a&gt; &lt;a href=\"/r/slashdiablo\"&gt;r/slashdiablo&lt;/a&gt; &lt;a href=\"/r/slaveleia\"&gt;r/slaveleia&lt;/a&gt; &lt;a href=\"/r/sleeptrain\"&gt;r/sleeptrain&lt;/a&gt; &lt;a href=\"/r/sleepy\"&gt;r/sleepy&lt;/a&gt; &lt;a href=\"/r/Slender_Man\"&gt;r/Slender_Man&lt;/a&gt; &lt;a href=\"/r/slightlyunsatisfying\"&gt;r/slightlyunsatisfying&lt;/a&gt; &lt;a href=\"/r/Slimemolds\"&gt;r/Slimemolds&lt;/a&gt; &lt;a href=\"/r/SlimmingWorld\"&gt;r/SlimmingWorld&lt;/a&gt; &lt;a href=\"/r/slingtv\"&gt;r/slingtv&lt;/a&gt; &lt;a href=\"/r/Slovenia\"&gt;r/Slovenia&lt;/a&gt; &lt;a href=\"/r/SlowTV\"&gt;r/SlowTV&lt;/a&gt; &lt;a href=\"/r/sludge\"&gt;r/sludge&lt;/a&gt; &lt;a href=\"/r/Slycooper\"&gt;r/Slycooper&lt;/a&gt; &lt;a href=\"/r/sm4sh\"&gt;r/sm4sh&lt;/a&gt; &lt;a href=\"/r/small_business_ideas\"&gt;r/small_business_ideas&lt;/a&gt; &lt;a href=\"/r/smallboobproblems\"&gt;r/smallboobproblems&lt;/a&gt; &lt;a href=\"/r/SmallDogBigBed\"&gt;r/SmallDogBigBed&lt;/a&gt; &lt;a href=\"/r/SmallYoutubers\"&gt;r/SmallYoutubers&lt;/a&gt; &lt;a href=\"/r/smartmirrors\"&gt;r/smartmirrors&lt;/a&gt; &lt;a href=\"/r/Smartphones\"&gt;r/Smartphones&lt;/a&gt; &lt;a href=\"/r/smartwatch\"&gt;r/smartwatch&lt;/a&gt; &lt;a href=\"/r/smashcirclejerk\"&gt;r/smashcirclejerk&lt;/a&gt; &lt;a href=\"/r/SmashingPumpkins\"&gt;r/SmashingPumpkins&lt;/a&gt; &lt;a href=\"/r/smashmemes\"&gt;r/smashmemes&lt;/a&gt; &lt;a href=\"/r/SMBCComics\"&gt;r/SMBCComics&lt;/a&gt; &lt;a href=\"/r/smitetraining\"&gt;r/smitetraining&lt;/a&gt; &lt;a href=\"/r/SmithAndWesson\"&gt;r/SmithAndWesson&lt;/a&gt; &lt;a href=\"/r/smokingcrabs\"&gt;r/smokingcrabs&lt;/a&gt; &lt;a href=\"/r/Smoothies\"&gt;r/Smoothies&lt;/a&gt; &lt;a href=\"/r/smoothslowmo_nsfw\"&gt;r/smoothslowmo_nsfw&lt;/a&gt; &lt;a href=\"/r/snails\"&gt;r/snails&lt;/a&gt; &lt;a href=\"/r/snapchatgeofilters\"&gt;r/snapchatgeofilters&lt;/a&gt; &lt;a href=\"/r/sneakerbots\"&gt;r/sneakerbots&lt;/a&gt; &lt;a href=\"/r/SneakyBackgroundFork\"&gt;r/SneakyBackgroundFork&lt;/a&gt; &lt;a href=\"/r/SneakyPaws\"&gt;r/SneakyPaws&lt;/a&gt; &lt;a href=\"/r/SnipsAir\"&gt;r/SnipsAir&lt;/a&gt; &lt;a href=\"/r/SNLirl\"&gt;r/SNLirl&lt;/a&gt; &lt;a href=\"/r/snowing\"&gt;r/snowing&lt;/a&gt; &lt;a href=\"/r/Snus\"&gt;r/Snus&lt;/a&gt; &lt;a href=\"/r/soanamnesis\"&gt;r/soanamnesis&lt;/a&gt; &lt;a href=\"/r/soccernerd\"&gt;r/soccernerd&lt;/a&gt; &lt;a href=\"/r/soccerspirits\"&gt;r/soccerspirits&lt;/a&gt; &lt;a href=\"/r/soccerstreams__\"&gt;r/soccerstreams__&lt;/a&gt; &lt;a href=\"/r/SoccerThunder\"&gt;r/SoccerThunder&lt;/a&gt; &lt;a href=\"/r/SocialDemocracy\"&gt;r/SocialDemocracy&lt;/a&gt; &lt;a href=\"/r/Socialistart\"&gt;r/Socialistart&lt;/a&gt; &lt;a href=\"/r/Socialistmusic\"&gt;r/Socialistmusic&lt;/a&gt; &lt;a href=\"/r/socialistprogrammers\"&gt;r/socialistprogrammers&lt;/a&gt; &lt;a href=\"/r/socialjustice101\"&gt;r/socialjustice101&lt;/a&gt; &lt;a href=\"/r/SocialMediaMarketing\"&gt;r/SocialMediaMarketing&lt;/a&gt; &lt;a href=\"/r/Soda\"&gt;r/Soda&lt;/a&gt; &lt;a href=\"/r/sodadungeon\"&gt;r/sodadungeon&lt;/a&gt; &lt;a href=\"/r/softscience\"&gt;r/softscience&lt;/a&gt; &lt;a href=\"/r/softwarearchitecture\"&gt;r/softwarearchitecture&lt;/a&gt; &lt;a href=\"/r/softwaretesting\"&gt;r/softwaretesting&lt;/a&gt; &lt;a href=\"/r/SolarDIY\"&gt;r/SolarDIY&lt;/a&gt; &lt;a href=\"/r/solarpunk\"&gt;r/solarpunk&lt;/a&gt; &lt;a href=\"/r/SolusProject\"&gt;r/SolusProject&lt;/a&gt; &lt;a href=\"/r/SombraMains\"&gt;r/SombraMains&lt;/a&gt; &lt;a href=\"/r/sonamains\"&gt;r/sonamains&lt;/a&gt; &lt;a href=\"/r/songaweek\"&gt;r/songaweek&lt;/a&gt; &lt;a href=\"/r/SongwritingPrompts\"&gt;r/SongwritingPrompts&lt;/a&gt; &lt;a href=\"/r/sonicshowerthoughts\"&gt;r/sonicshowerthoughts&lt;/a&gt; &lt;a href=\"/r/sony\"&gt;r/sony&lt;/a&gt; &lt;a href=\"/r/SonyXperia\"&gt;r/SonyXperia&lt;/a&gt; &lt;a href=\"/r/sooners\"&gt;r/sooners&lt;/a&gt; &lt;a href=\"/r/SootHouse\"&gt;r/SootHouse&lt;/a&gt; &lt;a href=\"/r/SOPA\"&gt;r/SOPA&lt;/a&gt; &lt;a href=\"/r/sophiknight\"&gt;r/sophiknight&lt;/a&gt; &lt;a href=\"/r/Sororities\"&gt;r/Sororities&lt;/a&gt; &lt;a href=\"/r/Sorosforprison\"&gt;r/Sorosforprison&lt;/a&gt; &lt;a href=\"/r/souleater\"&gt;r/souleater&lt;/a&gt; &lt;a href=\"/r/SoulKnight\"&gt;r/SoulKnight&lt;/a&gt; &lt;a href=\"/r/SoundCloudHipHop\"&gt;r/SoundCloudHipHop&lt;/a&gt; &lt;a href=\"/r/sounddesign\"&gt;r/sounddesign&lt;/a&gt; &lt;a href=\"/r/SoundsVintage\"&gt;r/SoundsVintage&lt;/a&gt; &lt;a href=\"/r/Southerncharm\"&gt;r/Southerncharm&lt;/a&gt; &lt;a href=\"/r/SouthgateMemes\"&gt;r/SouthgateMemes&lt;/a&gt; &lt;a href=\"/r/SouthJersey\"&gt;r/SouthJersey&lt;/a&gt; &lt;a href=\"/r/Sovereigncitizen\"&gt;r/Sovereigncitizen&lt;/a&gt; &lt;a href=\"/r/Space_Colonization\"&gt;r/Space_Colonization&lt;/a&gt; &lt;a href=\"/r/space_settlement\"&gt;r/space_settlement&lt;/a&gt; &lt;a href=\"/r/SpaceballsMemes\"&gt;r/SpaceballsMemes&lt;/a&gt; &lt;a href=\"/r/spacecats\"&gt;r/spacecats&lt;/a&gt; &lt;a href=\"/r/SpaceDandy\"&gt;r/SpaceDandy&lt;/a&gt; &lt;a href=\"/r/SpaceMusic\"&gt;r/SpaceMusic&lt;/a&gt; &lt;a href=\"/r/SpaceVideos\"&gt;r/SpaceVideos&lt;/a&gt; &lt;a href=\"/r/Sparkster\"&gt;r/Sparkster&lt;/a&gt; &lt;a href=\"/r/spartanrace\"&gt;r/spartanrace&lt;/a&gt; &lt;a href=\"/r/SpartaStartups\"&gt;r/SpartaStartups&lt;/a&gt; &lt;a href=\"/r/Spearfishing\"&gt;r/Spearfishing&lt;/a&gt; &lt;a href=\"/r/SpecialAccess\"&gt;r/SpecialAccess&lt;/a&gt; &lt;a href=\"/r/specialed\"&gt;r/specialed&lt;/a&gt; &lt;a href=\"/r/species\"&gt;r/species&lt;/a&gt; &lt;a href=\"/r/spelunky\"&gt;r/spelunky&lt;/a&gt; &lt;a href=\"/r/sphynx\"&gt;r/sphynx&lt;/a&gt; &lt;a href=\"/r/SpiceandWolf\"&gt;r/SpiceandWolf&lt;/a&gt; &lt;a href=\"/r/Spicy_Memes\"&gt;r/Spicy_Memes&lt;/a&gt; &lt;a href=\"/r/Spintires\"&gt;r/Spintires&lt;/a&gt; &lt;a href=\"/r/Splintercell\"&gt;r/Splintercell&lt;/a&gt; &lt;a href=\"/r/SpongeWatch\"&gt;r/SpongeWatch&lt;/a&gt; &lt;a href=\"/r/spooktober\"&gt;r/spooktober&lt;/a&gt; &lt;a href=\"/r/Spore\"&gt;r/Spore&lt;/a&gt; &lt;a href=\"/r/SporeSwap\"&gt;r/SporeSwap&lt;/a&gt; &lt;a href=\"/r/SportingKC\"&gt;r/SportingKC&lt;/a&gt; &lt;a href=\"/r/sportsjerseys\"&gt;r/sportsjerseys&lt;/a&gt; &lt;a href=\"/r/SportsPorn\"&gt;r/SportsPorn&lt;/a&gt; &lt;a href=\"/r/Sprechstunde\"&gt;r/Sprechstunde&lt;/a&gt; &lt;a href=\"/r/springfieldMO\"&gt;r/springfieldMO&lt;/a&gt; &lt;a href=\"/r/SpringPorn\"&gt;r/SpringPorn&lt;/a&gt; &lt;a href=\"/r/Sprinting\"&gt;r/Sprinting&lt;/a&gt; &lt;a href=\"/r/sproing\"&gt;r/sproing&lt;/a&gt; &lt;a href=\"/r/squash\"&gt;r/squash&lt;/a&gt; &lt;a href=\"/r/squidward_irl\"&gt;r/squidward_irl&lt;/a&gt; &lt;a href=\"/r/squirrels\"&gt;r/squirrels&lt;/a&gt; &lt;a href=\"/r/SquirrelsEatingPizza\"&gt;r/SquirrelsEatingPizza&lt;/a&gt; &lt;a href=\"/r/squishypuppers\"&gt;r/squishypuppers&lt;/a&gt; &lt;a href=\"/r/SR71\"&gt;r/SR71&lt;/a&gt; &lt;a href=\"/r/srilanka\"&gt;r/srilanka&lt;/a&gt; &lt;a href=\"/r/SRSFunny\"&gt;r/SRSFunny&lt;/a&gt; &lt;a href=\"/r/SRSGaming\"&gt;r/SRSGaming&lt;/a&gt; &lt;a href=\"/r/SSBBW_FANS\"&gt;r/SSBBW_FANS&lt;/a&gt; &lt;a href=\"/r/stadiumporn\"&gt;r/stadiumporn&lt;/a&gt; &lt;a href=\"/r/Stand\"&gt;r/Stand&lt;/a&gt; &lt;a href=\"/r/StandUpSpecials\"&gt;r/StandUpSpecials&lt;/a&gt; &lt;a href=\"/r/stanford\"&gt;r/stanford&lt;/a&gt; &lt;a href=\"/r/StannisTheMantis\"&gt;r/StannisTheMantis&lt;/a&gt; &lt;a href=\"/r/Staples\"&gt;r/Staples&lt;/a&gt; &lt;a href=\"/r/Star_Wars_Battlefront\"&gt;r/Star_Wars_Battlefront&lt;/a&gt; &lt;a href=\"/r/starbucksbaristas\"&gt;r/starbucksbaristas&lt;/a&gt; &lt;a href=\"/r/starcraft_strategy\"&gt;r/starcraft_strategy&lt;/a&gt; &lt;a href=\"/r/Starfield\"&gt;r/Starfield&lt;/a&gt; &lt;a href=\"/r/StartingStrength\"&gt;r/StartingStrength&lt;/a&gt; &lt;a href=\"/r/startpages\"&gt;r/startpages&lt;/a&gt; &lt;a href=\"/r/StartupAccelerators\"&gt;r/StartupAccelerators&lt;/a&gt; &lt;a href=\"/r/StarWarsArmada\"&gt;r/StarWarsArmada&lt;/a&gt; &lt;a href=\"/r/starwarscanon\"&gt;r/starwarscanon&lt;/a&gt; &lt;a href=\"/r/StarWarsCantina\"&gt;r/StarWarsCantina&lt;/a&gt; &lt;a href=\"/r/starwarscomics\"&gt;r/starwarscomics&lt;/a&gt; &lt;a href=\"/r/StarWarsForceArena\"&gt;r/StarWarsForceArena&lt;/a&gt; &lt;a href=\"/r/StarWarsTheories\"&gt;r/StarWarsTheories&lt;/a&gt; &lt;a href=\"/r/StateofDecay2\"&gt;r/StateofDecay2&lt;/a&gt; &lt;a href=\"/r/StateOfTheUnion\"&gt;r/StateOfTheUnion&lt;/a&gt; &lt;a href=\"/r/stationery\"&gt;r/stationery&lt;/a&gt; &lt;a href=\"/r/statuegropers\"&gt;r/statuegropers&lt;/a&gt; &lt;a href=\"/r/statusim\"&gt;r/statusim&lt;/a&gt; &lt;a href=\"/r/STD\"&gt;r/STD&lt;/a&gt; &lt;a href=\"/r/StealingTheShow\"&gt;r/StealingTheShow&lt;/a&gt; &lt;a href=\"/r/Steam_Link\"&gt;r/Steam_Link&lt;/a&gt; &lt;a href=\"/r/SteamedHams\"&gt;r/SteamedHams&lt;/a&gt; &lt;a href=\"/r/steamfriend\"&gt;r/steamfriend&lt;/a&gt; &lt;a href=\"/r/steamgiveaway\"&gt;r/steamgiveaway&lt;/a&gt; &lt;a href=\"/r/SteamOS\"&gt;r/SteamOS&lt;/a&gt; &lt;a href=\"/r/SteamPlay\"&gt;r/SteamPlay&lt;/a&gt; &lt;a href=\"/r/steamporn\"&gt;r/steamporn&lt;/a&gt; &lt;a href=\"/r/SteamReviews\"&gt;r/SteamReviews&lt;/a&gt; &lt;a href=\"/r/SteamTradingCards\"&gt;r/SteamTradingCards&lt;/a&gt; &lt;a href=\"/r/Steel_Division\"&gt;r/Steel_Division&lt;/a&gt; &lt;a href=\"/r/Steelbooks\"&gt;r/Steelbooks&lt;/a&gt; &lt;a href=\"/r/steemit\"&gt;r/steemit&lt;/a&gt; &lt;a href=\"/r/StephanieRayner\"&gt;r/StephanieRayner&lt;/a&gt; &lt;a href=\"/r/StephClaireSmith\"&gt;r/StephClaireSmith&lt;/a&gt; &lt;a href=\"/r/Stepmania\"&gt;r/Stepmania&lt;/a&gt; &lt;a href=\"/r/stevedangle\"&gt;r/stevedangle&lt;/a&gt; &lt;a href=\"/r/stevensuptic\"&gt;r/stevensuptic&lt;/a&gt; &lt;a href=\"/r/Stitchy\"&gt;r/Stitchy&lt;/a&gt; &lt;a href=\"/r/stock\"&gt;r/stock&lt;/a&gt; &lt;a href=\"/r/stockholm\"&gt;r/stockholm&lt;/a&gt; &lt;a href=\"/r/StolenValor\"&gt;r/StolenValor&lt;/a&gt; &lt;a href=\"/r/stonermetal\"&gt;r/stonermetal&lt;/a&gt; &lt;a href=\"/r/stop_motion\"&gt;r/stop_motion&lt;/a&gt; &lt;a href=\"/r/stopadvertising\"&gt;r/stopadvertising&lt;/a&gt; &lt;a href=\"/r/StopIDTheft\"&gt;r/StopIDTheft&lt;/a&gt; &lt;a href=\"/r/StopSelfHarm\"&gt;r/StopSelfHarm&lt;/a&gt; &lt;a href=\"/r/StopSpeeding\"&gt;r/StopSpeeding&lt;/a&gt; &lt;a href=\"/r/storiesfromapotato\"&gt;r/storiesfromapotato&lt;/a&gt; &lt;a href=\"/r/storj\"&gt;r/storj&lt;/a&gt; &lt;a href=\"/r/stormchasing\"&gt;r/stormchasing&lt;/a&gt; &lt;a href=\"/r/StormComing\"&gt;r/StormComing&lt;/a&gt; &lt;a href=\"/r/stormtroopersinphotos\"&gt;r/stormtroopersinphotos&lt;/a&gt; &lt;a href=\"/r/storyofseasons\"&gt;r/storyofseasons&lt;/a&gt; &lt;a href=\"/r/Storyshift\"&gt;r/Storyshift&lt;/a&gt; &lt;a href=\"/r/StPetersburgFL\"&gt;r/StPetersburgFL&lt;/a&gt; &lt;a href=\"/r/straightedge\"&gt;r/straightedge&lt;/a&gt; &lt;a href=\"/r/Stratis\"&gt;r/Stratis&lt;/a&gt; &lt;a href=\"/r/streaming\"&gt;r/streaming&lt;/a&gt; &lt;a href=\"/r/streetlightmanifesto\"&gt;r/streetlightmanifesto&lt;/a&gt; &lt;a href=\"/r/StreetwearSales\"&gt;r/StreetwearSales&lt;/a&gt; &lt;a href=\"/r/Stress\"&gt;r/Stress&lt;/a&gt; &lt;a href=\"/r/stronglifts\"&gt;r/stronglifts&lt;/a&gt; &lt;a href=\"/r/Stuck10YearsBehind\"&gt;r/Stuck10YearsBehind&lt;/a&gt; &lt;a href=\"/r/stuckgirls\"&gt;r/stuckgirls&lt;/a&gt; &lt;a href=\"/r/studentfood\"&gt;r/studentfood&lt;/a&gt; &lt;a href=\"/r/studentloandefaulters\"&gt;r/studentloandefaulters&lt;/a&gt; &lt;a href=\"/r/study\"&gt;r/study&lt;/a&gt; &lt;a href=\"/r/studyAbroad\"&gt;r/studyAbroad&lt;/a&gt; &lt;a href=\"/r/studytips\"&gt;r/studytips&lt;/a&gt; &lt;a href=\"/r/Stutter\"&gt;r/Stutter&lt;/a&gt; &lt;a href=\"/r/Sub4Sub\"&gt;r/Sub4Sub&lt;/a&gt; &lt;a href=\"/r/Subaru_Outback\"&gt;r/Subaru_Outback&lt;/a&gt; &lt;a href=\"/r/subaruimpreza\"&gt;r/subaruimpreza&lt;/a&gt; &lt;a href=\"/r/SublimeText\"&gt;r/SublimeText&lt;/a&gt; &lt;a href=\"/r/Subliminal\"&gt;r/Subliminal&lt;/a&gt; &lt;a href=\"/r/subreddit\"&gt;r/subreddit&lt;/a&gt; &lt;a href=\"/r/SubredditDramaDrama\"&gt;r/SubredditDramaDrama&lt;/a&gt; &lt;a href=\"/r/SubscriptionBoxes\"&gt;r/SubscriptionBoxes&lt;/a&gt; &lt;a href=\"/r/subsithoughtwerefake\"&gt;r/subsithoughtwerefake&lt;/a&gt; &lt;a href=\"/r/SuburbanFarming\"&gt;r/SuburbanFarming&lt;/a&gt; &lt;a href=\"/r/Suburbanhell\"&gt;r/Suburbanhell&lt;/a&gt; &lt;a href=\"/r/subway\"&gt;r/subway&lt;/a&gt; &lt;a href=\"/r/subwaysubway\"&gt;r/subwaysubway&lt;/a&gt; &lt;a href=\"/r/suchislifeinmoscow\"&gt;r/suchislifeinmoscow&lt;/a&gt; &lt;a href=\"/r/suddenlyalabama\"&gt;r/suddenlyalabama&lt;/a&gt; &lt;a href=\"/r/SuddenlyIRealized\"&gt;r/SuddenlyIRealized&lt;/a&gt; &lt;a href=\"/r/SuddenlyLesbian\"&gt;r/SuddenlyLesbian&lt;/a&gt; &lt;a href=\"/r/Sufjan\"&gt;r/Sufjan&lt;/a&gt; &lt;a href=\"/r/sugarfree\"&gt;r/sugarfree&lt;/a&gt; &lt;a href=\"/r/SuicideBereavement\"&gt;r/SuicideBereavement&lt;/a&gt; &lt;a href=\"/r/Suicidegirlshopeless\"&gt;r/Suicidegirlshopeless&lt;/a&gt; &lt;a href=\"/r/suicidology\"&gt;r/suicidology&lt;/a&gt; &lt;a href=\"/r/SummerGlau\"&gt;r/SummerGlau&lt;/a&gt; &lt;a href=\"/r/SummerPorn\"&gt;r/SummerPorn&lt;/a&gt; &lt;a href=\"/r/Summit1G\"&gt;r/Summit1G&lt;/a&gt; &lt;a href=\"/r/summoners\"&gt;r/summoners&lt;/a&gt; &lt;a href=\"/r/Sumo\"&gt;r/Sumo&lt;/a&gt; &lt;a href=\"/r/sunlesssea\"&gt;r/sunlesssea&lt;/a&gt; &lt;a href=\"/r/Sup\"&gt;r/Sup&lt;/a&gt; &lt;a href=\"/r/SuperMega\"&gt;r/SuperMega&lt;/a&gt; &lt;a href=\"/r/SuperMegaBaseball\"&gt;r/SuperMegaBaseball&lt;/a&gt; &lt;a href=\"/r/superplanetdolan\"&gt;r/superplanetdolan&lt;/a&gt; &lt;a href=\"/r/supersentai\"&gt;r/supersentai&lt;/a&gt; &lt;a href=\"/r/SuperStarBTS\"&gt;r/SuperStarBTS&lt;/a&gt; &lt;a href=\"/r/superstarsmtown\"&gt;r/superstarsmtown&lt;/a&gt; &lt;a href=\"/r/SurfaceGaming\"&gt;r/SurfaceGaming&lt;/a&gt; &lt;a href=\"/r/SurfaceLinux\"&gt;r/SurfaceLinux&lt;/a&gt; &lt;a href=\"/r/surpriselightsabers\"&gt;r/surpriselightsabers&lt;/a&gt; &lt;a href=\"/r/SurrealApprovals\"&gt;r/SurrealApprovals&lt;/a&gt; &lt;a href=\"/r/SurrealLore\"&gt;r/SurrealLore&lt;/a&gt; &lt;a href=\"/r/surrealtraa\"&gt;r/surrealtraa&lt;/a&gt; &lt;a href=\"/r/Surveying\"&gt;r/Surveying&lt;/a&gt; &lt;a href=\"/r/SurvivalGaming\"&gt;r/SurvivalGaming&lt;/a&gt; &lt;a href=\"/r/survivalhorror\"&gt;r/survivalhorror&lt;/a&gt; &lt;a href=\"/r/survivetheculling\"&gt;r/survivetheculling&lt;/a&gt; &lt;a href=\"/r/susancoffey\"&gt;r/susancoffey&lt;/a&gt; &lt;a href=\"/r/SushiRoll\"&gt;r/SushiRoll&lt;/a&gt; &lt;a href=\"/r/SVU\"&gt;r/SVU&lt;/a&gt; &lt;a href=\"/r/swachhcoin\"&gt;r/swachhcoin&lt;/a&gt; &lt;a href=\"/r/SwainMains\"&gt;r/SwainMains&lt;/a&gt; &lt;a href=\"/r/sweatcoin\"&gt;r/sweatcoin&lt;/a&gt; &lt;a href=\"/r/SweaterDress\"&gt;r/SweaterDress&lt;/a&gt; &lt;a href=\"/r/swgemu\"&gt;r/swgemu&lt;/a&gt; &lt;a href=\"/r/swgoh_guilds\"&gt;r/swgoh_guilds&lt;/a&gt; &lt;a href=\"/r/SwingDancing\"&gt;r/SwingDancing&lt;/a&gt; &lt;a href=\"/r/swissalpsmining\"&gt;r/swissalpsmining&lt;/a&gt; &lt;a href=\"/r/SWlegion\"&gt;r/SWlegion&lt;/a&gt; &lt;a href=\"/r/swoletariat\"&gt;r/swoletariat&lt;/a&gt; &lt;a href=\"/r/SwordAndScale\"&gt;r/SwordAndScale&lt;/a&gt; &lt;a href=\"/r/SXSW\"&gt;r/SXSW&lt;/a&gt; &lt;a href=\"/r/SymmetraMains\"&gt;r/SymmetraMains&lt;/a&gt; &lt;a href=\"/r/symphonicmetal\"&gt;r/symphonicmetal&lt;/a&gt; &lt;a href=\"/r/synapseai\"&gt;r/synapseai&lt;/a&gt; &lt;a href=\"/r/Synchronicities\"&gt;r/Synchronicities&lt;/a&gt; &lt;a href=\"/r/Synesthesia\"&gt;r/Synesthesia&lt;/a&gt; &lt;a href=\"/r/synthesizercirclejerk\"&gt;r/synthesizercirclejerk&lt;/a&gt; &lt;a href=\"/r/synthpop\"&gt;r/synthpop&lt;/a&gt; &lt;a href=\"/r/Syracuse\"&gt;r/Syracuse&lt;/a&gt; &lt;a href=\"/r/Syria\"&gt;r/Syria&lt;/a&gt; &lt;a href=\"/r/SyrianCirclejerkWar\"&gt;r/SyrianCirclejerkWar&lt;/a&gt; &lt;a href=\"/r/SysAdminBlogs\"&gt;r/SysAdminBlogs&lt;/a&gt; &lt;a href=\"/r/sysadmintools\"&gt;r/sysadmintools&lt;/a&gt; &lt;a href=\"/r/systemofadown\"&gt;r/systemofadown&lt;/a&gt; &lt;a href=\"/r/systems\"&gt;r/systems&lt;/a&gt; &lt;/p&gt;\n\n&lt;p&gt;&amp;#x200B;&lt;/p&gt;\n\n&lt;p&gt;&lt;a href=\"/r/tabdetective\"&gt;r/tabdetective&lt;/a&gt; &lt;a href=\"/r/tablets\"&gt;r/tablets&lt;/a&gt; &lt;a href=\"/r/TabooFX\"&gt;r/TabooFX&lt;/a&gt; &lt;a href=\"/r/Tachanka\"&gt;r/Tachanka&lt;/a&gt; &lt;a href=\"/r/tacticalbarbell\"&gt;r/tacticalbarbell&lt;/a&gt; &lt;a href=\"/r/taekwondo\"&gt;r/taekwondo&lt;/a&gt; &lt;a href=\"/r/tahoe\"&gt;r/tahoe&lt;/a&gt; &lt;a href=\"/r/taijiquan\"&gt;r/taijiquan&lt;/a&gt; &lt;a href=\"/r/takecareofmyplant\"&gt;r/takecareofmyplant&lt;/a&gt; &lt;a href=\"/r/TalesFromAutoRepair\"&gt;r/TalesFromAutoRepair&lt;/a&gt; &lt;a href=\"/r/talesfromdesigners\"&gt;r/talesfromdesigners&lt;/a&gt; &lt;a href=\"/r/TalesFromDispatch\"&gt;r/TalesFromDispatch&lt;/a&gt; &lt;a href=\"/r/TalesFromEMS\"&gt;r/TalesFromEMS&lt;/a&gt; &lt;a href=\"/r/TalesFromFastFood\"&gt;r/TalesFromFastFood&lt;/a&gt; &lt;a href=\"/r/TalesFromHousekeeping\"&gt;r/TalesFromHousekeeping&lt;/a&gt; &lt;a href=\"/r/Talesfromrimworld\"&gt;r/Talesfromrimworld&lt;/a&gt; &lt;a href=\"/r/TalesFromTheMilitary\"&gt;r/TalesFromTheMilitary&lt;/a&gt; &lt;a href=\"/r/TalesFromYourBank\"&gt;r/TalesFromYourBank&lt;/a&gt; &lt;a href=\"/r/TalesFromYourBarista\"&gt;r/TalesFromYourBarista&lt;/a&gt; &lt;a href=\"/r/TalesoftheConvention\"&gt;r/TalesoftheConvention&lt;/a&gt; &lt;a href=\"/r/TaliyahMains\"&gt;r/TaliyahMains&lt;/a&gt; &lt;a href=\"/r/TalkShowGirls\"&gt;r/TalkShowGirls&lt;/a&gt; &lt;a href=\"/r/talkshows\"&gt;r/talkshows&lt;/a&gt; &lt;a href=\"/r/TalkTherapy\"&gt;r/TalkTherapy&lt;/a&gt; &lt;a href=\"/r/Tallahassee\"&gt;r/Tallahassee&lt;/a&gt; &lt;a href=\"/r/tallfashionadvice\"&gt;r/tallfashionadvice&lt;/a&gt; &lt;a href=\"/r/tampabayrays\"&gt;r/tampabayrays&lt;/a&gt; &lt;a href=\"/r/tanks\"&gt;r/tanks&lt;/a&gt; &lt;a href=\"/r/tapirs\"&gt;r/tapirs&lt;/a&gt; &lt;a href=\"/r/tardcat\"&gt;r/tardcat&lt;/a&gt; &lt;a href=\"/r/taskmaster\"&gt;r/taskmaster&lt;/a&gt; &lt;a href=\"/r/TattooArt\"&gt;r/TattooArt&lt;/a&gt; &lt;a href=\"/r/Tau40K\"&gt;r/Tau40K&lt;/a&gt; &lt;a href=\"/r/Tautology\"&gt;r/Tautology&lt;/a&gt; &lt;a href=\"/r/Taxidermy\"&gt;r/Taxidermy&lt;/a&gt; &lt;a href=\"/r/taxmarch\"&gt;r/taxmarch&lt;/a&gt; &lt;a href=\"/r/taxpros\"&gt;r/taxpros&lt;/a&gt; &lt;a href=\"/r/taylormariehill\"&gt;r/taylormariehill&lt;/a&gt; &lt;a href=\"/r/TaylorMomsen\"&gt;r/TaylorMomsen&lt;/a&gt; &lt;a href=\"/r/TaylorSwiftBreasts\"&gt;r/TaylorSwiftBreasts&lt;/a&gt; &lt;a href=\"/r/Tayne\"&gt;r/Tayne&lt;/a&gt; &lt;a href=\"/r/tdi\"&gt;r/tdi&lt;/a&gt; &lt;a href=\"/r/teachinginjapan\"&gt;r/teachinginjapan&lt;/a&gt; &lt;a href=\"/r/teachinginkorea\"&gt;r/teachinginkorea&lt;/a&gt; &lt;a href=\"/r/teamliquid\"&gt;r/teamliquid&lt;/a&gt; &lt;a href=\"/r/TeardropTrailers\"&gt;r/TeardropTrailers&lt;/a&gt; &lt;a href=\"/r/technawwlogy\"&gt;r/technawwlogy&lt;/a&gt; &lt;a href=\"/r/TechnicalDeathMetal\"&gt;r/TechnicalDeathMetal&lt;/a&gt; &lt;a href=\"/r/TechnicallyCorrect\"&gt;r/TechnicallyCorrect&lt;/a&gt; &lt;a href=\"/r/techsupportanimals\"&gt;r/techsupportanimals&lt;/a&gt; &lt;a href=\"/r/TeemoTalk\"&gt;r/TeemoTalk&lt;/a&gt; &lt;a href=\"/r/TeenAmIUgly\"&gt;r/TeenAmIUgly&lt;/a&gt; &lt;a href=\"/r/TeenMFA\"&gt;r/TeenMFA&lt;/a&gt; &lt;a href=\"/r/teenrelationships\"&gt;r/teenrelationships&lt;/a&gt; &lt;a href=\"/r/teentitans\"&gt;r/teentitans&lt;/a&gt; &lt;a href=\"/r/TeenWolf\"&gt;r/TeenWolf&lt;/a&gt; &lt;a href=\"/r/teethdrumming\"&gt;r/teethdrumming&lt;/a&gt; &lt;a href=\"/r/tekkit\"&gt;r/tekkit&lt;/a&gt; &lt;a href=\"/r/telecaster\"&gt;r/telecaster&lt;/a&gt; &lt;a href=\"/r/telecommuting\"&gt;r/telecommuting&lt;/a&gt; &lt;a href=\"/r/TelegramBots\"&gt;r/TelegramBots&lt;/a&gt; &lt;a href=\"/r/TelegramStickersShare\"&gt;r/TelegramStickersShare&lt;/a&gt; &lt;a href=\"/r/televisioncirclejerk\"&gt;r/televisioncirclejerk&lt;/a&gt; &lt;a href=\"/r/TelevisionPosterPorn\"&gt;r/TelevisionPosterPorn&lt;/a&gt; &lt;a href=\"/r/TellReddit\"&gt;r/TellReddit&lt;/a&gt; &lt;a href=\"/r/Tempe\"&gt;r/Tempe&lt;/a&gt; &lt;a href=\"/r/Temple\"&gt;r/Temple&lt;/a&gt; &lt;a href=\"/r/templeofthephil\"&gt;r/templeofthephil&lt;/a&gt; &lt;a href=\"/r/TenYearsAgo\"&gt;r/TenYearsAgo&lt;/a&gt; &lt;a href=\"/r/tequila\"&gt;r/tequila&lt;/a&gt; &lt;a href=\"/r/terencemckenna\"&gt;r/terencemckenna&lt;/a&gt; &lt;a href=\"/r/TerrariaDesign\"&gt;r/TerrariaDesign&lt;/a&gt; &lt;a href=\"/r/tesdcares\"&gt;r/tesdcares&lt;/a&gt; &lt;a href=\"/r/TeslaLounge\"&gt;r/TeslaLounge&lt;/a&gt; &lt;a href=\"/r/TeslaPorn\"&gt;r/TeslaPorn&lt;/a&gt; &lt;a href=\"/r/test\"&gt;r/test&lt;/a&gt; &lt;a href=\"/r/Tetris99\"&gt;r/Tetris99&lt;/a&gt; &lt;a href=\"/r/TexasPolitics\"&gt;r/TexasPolitics&lt;/a&gt; &lt;a href=\"/r/TexasTech\"&gt;r/TexasTech&lt;/a&gt; &lt;a href=\"/r/textdoor\"&gt;r/textdoor&lt;/a&gt; &lt;a href=\"/r/tf_irl\"&gt;r/tf_irl&lt;/a&gt; &lt;a href=\"/r/TFABAARBI\"&gt;r/TFABAARBI&lt;/a&gt; &lt;a href=\"/r/TFABLinePorn\"&gt;r/TFABLinePorn&lt;/a&gt; &lt;a href=\"/r/tfc\"&gt;r/tfc&lt;/a&gt; &lt;a href=\"/r/ThailandTourism\"&gt;r/ThailandTourism&lt;/a&gt; &lt;a href=\"/r/thalassaphobia\"&gt;r/thalassaphobia&lt;/a&gt; &lt;a href=\"/r/that_Poppy\"&gt;r/that_Poppy&lt;/a&gt; &lt;a href=\"/r/thatcouldvebeenworse\"&gt;r/thatcouldvebeenworse&lt;/a&gt; &lt;a href=\"/r/thatescalatedquickly\"&gt;r/thatescalatedquickly&lt;/a&gt; &lt;a href=\"/r/thatsneat\"&gt;r/thatsneat&lt;/a&gt; &lt;a href=\"/r/ThatsWhatSheSaid\"&gt;r/ThatsWhatSheSaid&lt;/a&gt; &lt;a href=\"/r/The48LawsOfPower\"&gt;r/The48LawsOfPower&lt;/a&gt; &lt;a href=\"/r/the_darnold\"&gt;r/the_darnold&lt;/a&gt; &lt;a href=\"/r/The_Dotard\"&gt;r/The_Dotard&lt;/a&gt; &lt;a href=\"/r/The_Europe\"&gt;r/The_Europe&lt;/a&gt; &lt;a href=\"/r/The_Farage\"&gt;r/The_Farage&lt;/a&gt; &lt;a href=\"/r/The_Keepers\"&gt;r/The_Keepers&lt;/a&gt; &lt;a href=\"/r/The_Leftorium\"&gt;r/The_Leftorium&lt;/a&gt; &lt;a href=\"/r/the_mouse\"&gt;r/the_mouse&lt;/a&gt; &lt;a href=\"/r/The_MuellerMeltdown\"&gt;r/The_MuellerMeltdown&lt;/a&gt; &lt;a href=\"/r/The_Wall\"&gt;r/The_Wall&lt;/a&gt; &lt;a href=\"/r/TheAgora\"&gt;r/TheAgora&lt;/a&gt; &lt;a href=\"/r/TheArtifice\"&gt;r/TheArtifice&lt;/a&gt; &lt;a href=\"/r/TheB1G\"&gt;r/TheB1G&lt;/a&gt; &lt;a href=\"/r/TheBeatles\"&gt;r/TheBeatles&lt;/a&gt; &lt;a href=\"/r/TheBigLezShow\"&gt;r/TheBigLezShow&lt;/a&gt; &lt;a href=\"/r/thebindingofisaac\"&gt;r/thebindingofisaac&lt;/a&gt; &lt;a href=\"/r/theboudoir\"&gt;r/theboudoir&lt;/a&gt; &lt;a href=\"/r/TheBrightSide\"&gt;r/TheBrightSide&lt;/a&gt; &lt;a href=\"/r/TheCannalysts\"&gt;r/TheCannalysts&lt;/a&gt; &lt;a href=\"/r/TheChills\"&gt;r/TheChills&lt;/a&gt; &lt;a href=\"/r/TheCloneWars\"&gt;r/TheCloneWars&lt;/a&gt; &lt;a href=\"/r/TheCompletionist\"&gt;r/TheCompletionist&lt;/a&gt; &lt;a href=\"/r/TheCulture\"&gt;r/TheCulture&lt;/a&gt; &lt;a href=\"/r/TheDarwinProject\"&gt;r/TheDarwinProject&lt;/a&gt; &lt;a href=\"/r/TheDearHunter\"&gt;r/TheDearHunter&lt;/a&gt; &lt;a href=\"/r/TheDickShow\"&gt;r/TheDickShow&lt;/a&gt; &lt;a href=\"/r/thedivisionclans\"&gt;r/thedivisionclans&lt;/a&gt; &lt;a href=\"/r/TheDogPaw\"&gt;r/TheDogPaw&lt;/a&gt; &lt;a href=\"/r/thedoors\"&gt;r/thedoors&lt;/a&gt; &lt;a href=\"/r/TheeHive\"&gt;r/TheeHive&lt;/a&gt; &lt;a href=\"/r/TheFarSide\"&gt;r/TheFarSide&lt;/a&gt; &lt;a href=\"/r/thefighterandthekid\"&gt;r/thefighterandthekid&lt;/a&gt; &lt;a href=\"/r/TheFrontBottoms\"&gt;r/TheFrontBottoms&lt;/a&gt; &lt;a href=\"/r/thegdstudio\"&gt;r/thegdstudio&lt;/a&gt; &lt;a href=\"/r/TheGifted\"&gt;r/TheGifted&lt;/a&gt; &lt;a href=\"/r/TheGlassCannonPodcast\"&gt;r/TheGlassCannonPodcast&lt;/a&gt; &lt;a href=\"/r/TheGreatWar\"&gt;r/TheGreatWar&lt;/a&gt; &lt;a href=\"/r/TheGriffonsSaddlebag\"&gt;r/TheGriffonsSaddlebag&lt;/a&gt; &lt;a href=\"/r/TheHearth\"&gt;r/TheHearth&lt;/a&gt; &lt;a href=\"/r/theHunter\"&gt;r/theHunter&lt;/a&gt; &lt;a href=\"/r/theinternetofshit\"&gt;r/theinternetofshit&lt;/a&gt; &lt;a href=\"/r/theJoeBuddenPodcast\"&gt;r/theJoeBuddenPodcast&lt;/a&gt; &lt;a href=\"/r/THEKEYOFFICIAL\"&gt;r/THEKEYOFFICIAL&lt;/a&gt; &lt;a href=\"/r/thelastofusfactions\"&gt;r/thelastofusfactions&lt;/a&gt; &lt;a href=\"/r/thelema\"&gt;r/thelema&lt;/a&gt; &lt;a href=\"/r/TheLetterH\"&gt;r/TheLetterH&lt;/a&gt; &lt;a href=\"/r/TheMarvelousMrsMaisel\"&gt;r/TheMarvelousMrsMaisel&lt;/a&gt; &lt;a href=\"/r/TheMaskedSinger\"&gt;r/TheMaskedSinger&lt;/a&gt; &lt;a href=\"/r/TheMassive\"&gt;r/TheMassive&lt;/a&gt; &lt;a href=\"/r/ThemeParkitect\"&gt;r/ThemeParkitect&lt;/a&gt; &lt;a href=\"/r/themoddingofisaac\"&gt;r/themoddingofisaac&lt;/a&gt; &lt;a href=\"/r/themountaingoats\"&gt;r/themountaingoats&lt;/a&gt; &lt;a href=\"/r/TheNational\"&gt;r/TheNational&lt;/a&gt; &lt;a href=\"/r/theneedledrop\"&gt;r/theneedledrop&lt;/a&gt; &lt;a href=\"/r/Thenewsroom\"&gt;r/Thenewsroom&lt;/a&gt; &lt;a href=\"/r/TheNightmareBeneath\"&gt;r/TheNightmareBeneath&lt;/a&gt; &lt;a href=\"/r/TheNightOf\"&gt;r/TheNightOf&lt;/a&gt; &lt;a href=\"/r/TheNSFWClub\"&gt;r/TheNSFWClub&lt;/a&gt; &lt;a href=\"/r/theNvidiaShield\"&gt;r/theNvidiaShield&lt;/a&gt; &lt;a href=\"/r/TheOceanCleanup\"&gt;r/TheOceanCleanup&lt;/a&gt; &lt;a href=\"/r/TheOCS\"&gt;r/TheOCS&lt;/a&gt; &lt;a href=\"/r/theodd1sout\"&gt;r/theodd1sout&lt;/a&gt; &lt;a href=\"/r/theofficegifs\"&gt;r/theofficegifs&lt;/a&gt; &lt;a href=\"/r/theofficememes\"&gt;r/theofficememes&lt;/a&gt; &lt;a href=\"/r/TheOriginals\"&gt;r/TheOriginals&lt;/a&gt; &lt;a href=\"/r/TheOverload\"&gt;r/TheOverload&lt;/a&gt; &lt;a href=\"/r/TheoVon\"&gt;r/TheoVon&lt;/a&gt; &lt;a href=\"/r/ThePopcornStand\"&gt;r/ThePopcornStand&lt;/a&gt; &lt;a href=\"/r/therapists\"&gt;r/therapists&lt;/a&gt; &lt;a href=\"/r/theredditor\"&gt;r/theredditor&lt;/a&gt; &lt;a href=\"/r/TheRedDress\"&gt;r/TheRedDress&lt;/a&gt; &lt;a href=\"/r/TheRedLion\"&gt;r/TheRedLion&lt;/a&gt; &lt;a href=\"/r/TheSecretWorld\"&gt;r/TheSecretWorld&lt;/a&gt; &lt;a href=\"/r/TheSimsBuilding\"&gt;r/TheSimsBuilding&lt;/a&gt; &lt;a href=\"/r/thesmiths\"&gt;r/thesmiths&lt;/a&gt; &lt;a href=\"/r/TheStaircase\"&gt;r/TheStaircase&lt;/a&gt; &lt;a href=\"/r/TheStrain\"&gt;r/TheStrain&lt;/a&gt; &lt;a href=\"/r/thesuperbowl\"&gt;r/thesuperbowl&lt;/a&gt; &lt;a href=\"/r/TheSurvivalGuide\"&gt;r/TheSurvivalGuide&lt;/a&gt; &lt;a href=\"/r/theticket\"&gt;r/theticket&lt;/a&gt; &lt;a href=\"/r/theunexplained\"&gt;r/theunexplained&lt;/a&gt; &lt;a href=\"/r/TheValleyFolk\"&gt;r/TheValleyFolk&lt;/a&gt; &lt;a href=\"/r/thevenomsite\"&gt;r/thevenomsite&lt;/a&gt; &lt;a href=\"/r/TheWaterLew\"&gt;r/TheWaterLew&lt;/a&gt; &lt;a href=\"/r/TheWitness\"&gt;r/TheWitness&lt;/a&gt; &lt;a href=\"/r/TheWolfAmongUs\"&gt;r/TheWolfAmongUs&lt;/a&gt; &lt;a href=\"/r/theworldnews\"&gt;r/theworldnews&lt;/a&gt; &lt;a href=\"/r/theydidthemeth\"&gt;r/theydidthemeth&lt;/a&gt; &lt;a href=\"/r/ThingsFightingIdiots\"&gt;r/ThingsFightingIdiots&lt;/a&gt; &lt;a href=\"/r/ThingsIWishIKnew\"&gt;r/ThingsIWishIKnew&lt;/a&gt; &lt;a href=\"/r/thirdworldproblems\"&gt;r/thirdworldproblems&lt;/a&gt; &lt;a href=\"/r/ThisCrazyBitch\"&gt;r/ThisCrazyBitch&lt;/a&gt; &lt;a href=\"/r/thisisntwhoweare\"&gt;r/thisisntwhoweare&lt;/a&gt; &lt;a href=\"/r/thisweekinreview\"&gt;r/thisweekinreview&lt;/a&gt; &lt;a href=\"/r/ThoseEyes\"&gt;r/ThoseEyes&lt;/a&gt; &lt;a href=\"/r/thot_patrol\"&gt;r/thot_patrol&lt;/a&gt; &lt;a href=\"/r/thrashmetal\"&gt;r/thrashmetal&lt;/a&gt; &lt;a href=\"/r/Thrift\"&gt;r/Thrift&lt;/a&gt; &lt;a href=\"/r/ThriftyThread\"&gt;r/ThriftyThread&lt;/a&gt; &lt;a href=\"/r/thronescomics\"&gt;r/thronescomics&lt;/a&gt; &lt;a href=\"/r/thuglife\"&gt;r/thuglife&lt;/a&gt; &lt;a href=\"/r/TiADiscussion\"&gt;r/TiADiscussion&lt;/a&gt; &lt;a href=\"/r/TIDTRT\"&gt;r/TIDTRT&lt;/a&gt; &lt;a href=\"/r/TigerBelly\"&gt;r/TigerBelly&lt;/a&gt; &lt;a href=\"/r/tightsandlooseclothes\"&gt;r/tightsandlooseclothes&lt;/a&gt; &lt;a href=\"/r/tijuana\"&gt;r/tijuana&lt;/a&gt; &lt;a href=\"/r/Tiki\"&gt;r/Tiki&lt;/a&gt; &lt;a href=\"/r/tildes\"&gt;r/tildes&lt;/a&gt; &lt;a href=\"/r/timbers\"&gt;r/timbers&lt;/a&gt; &lt;a href=\"/r/Timeless\"&gt;r/Timeless&lt;/a&gt; &lt;a href=\"/r/TimeManagement\"&gt;r/TimeManagement&lt;/a&gt; &lt;a href=\"/r/timeshiftedmemes\"&gt;r/timeshiftedmemes&lt;/a&gt; &lt;a href=\"/r/Tinderpickuplines\"&gt;r/Tinderpickuplines&lt;/a&gt; &lt;a href=\"/r/tinytower\"&gt;r/tinytower&lt;/a&gt; &lt;a href=\"/r/tiodopave\"&gt;r/tiodopave&lt;/a&gt; &lt;a href=\"/r/tipoftheday\"&gt;r/tipoftheday&lt;/a&gt; &lt;a href=\"/r/Titanfall_2_\"&gt;r/Titanfall_2_&lt;/a&gt; &lt;a href=\"/r/TLCsisterwives\"&gt;r/TLCsisterwives&lt;/a&gt; &lt;a href=\"/r/TNG\"&gt;r/TNG&lt;/a&gt; &lt;a href=\"/r/TNOmod\"&gt;r/TNOmod&lt;/a&gt; &lt;a href=\"/r/ToastersGW\"&gt;r/ToastersGW&lt;/a&gt; &lt;a href=\"/r/Toastmasters\"&gt;r/Toastmasters&lt;/a&gt; &lt;a href=\"/r/TodayIAte\"&gt;r/TodayIAte&lt;/a&gt; &lt;a href=\"/r/todayifuckedup\"&gt;r/todayifuckedup&lt;/a&gt; &lt;a href=\"/r/todoist\"&gt;r/todoist&lt;/a&gt; &lt;a href=\"/r/toiletviews\"&gt;r/toiletviews&lt;/a&gt; &lt;a href=\"/r/toledo\"&gt;r/toledo&lt;/a&gt; &lt;a href=\"/r/TolkienArt\"&gt;r/TolkienArt&lt;/a&gt; &lt;a href=\"/r/toloveru\"&gt;r/toloveru&lt;/a&gt; &lt;a href=\"/r/TomAndJerryMemes\"&gt;r/TomAndJerryMemes&lt;/a&gt; &lt;a href=\"/r/tombprospectors\"&gt;r/tombprospectors&lt;/a&gt; &lt;a href=\"/r/tomhiddleston\"&gt;r/tomhiddleston&lt;/a&gt; &lt;a href=\"/r/TomSka\"&gt;r/TomSka&lt;/a&gt; &lt;a href=\"/r/TongueOutHounds\"&gt;r/TongueOutHounds&lt;/a&gt; &lt;a href=\"/r/tonsilstones\"&gt;r/tonsilstones&lt;/a&gt; &lt;a href=\"/r/ToobAmps\"&gt;r/ToobAmps&lt;/a&gt; &lt;a href=\"/r/tookyoulongenough\"&gt;r/tookyoulongenough&lt;/a&gt; &lt;a href=\"/r/toomanypillows\"&gt;r/toomanypillows&lt;/a&gt; &lt;a href=\"/r/toontownrewritten\"&gt;r/toontownrewritten&lt;/a&gt; &lt;a href=\"/r/TopChef\"&gt;r/TopChef&lt;/a&gt; &lt;a href=\"/r/topl\"&gt;r/topl&lt;/a&gt; &lt;a href=\"/r/Torchwood\"&gt;r/Torchwood&lt;/a&gt; &lt;a href=\"/r/tornado\"&gt;r/tornado&lt;/a&gt; &lt;a href=\"/r/torontoJobs\"&gt;r/torontoJobs&lt;/a&gt; &lt;a href=\"/r/torties\"&gt;r/torties&lt;/a&gt; &lt;a href=\"/r/tortoise\"&gt;r/tortoise&lt;/a&gt; &lt;a href=\"/r/TotalWarArena\"&gt;r/TotalWarArena&lt;/a&gt; &lt;a href=\"/r/touchfluffytail\"&gt;r/touchfluffytail&lt;/a&gt; &lt;a href=\"/r/TOUHOUMUSIC\"&gt;r/TOUHOUMUSIC&lt;/a&gt; &lt;a href=\"/r/tourdefrance\"&gt;r/tourdefrance&lt;/a&gt; &lt;a href=\"/r/toycameras\"&gt;r/toycameras&lt;/a&gt; &lt;a href=\"/r/toyexchange\"&gt;r/toyexchange&lt;/a&gt; &lt;a href=\"/r/toys\"&gt;r/toys&lt;/a&gt; &lt;a href=\"/r/TQDC\"&gt;r/TQDC&lt;/a&gt; &lt;a href=\"/r/TR8R\"&gt;r/TR8R&lt;/a&gt; &lt;a href=\"/r/Trackballs\"&gt;r/Trackballs&lt;/a&gt; &lt;a href=\"/r/Trackdays\"&gt;r/Trackdays&lt;/a&gt; &lt;a href=\"/r/TrackGirls\"&gt;r/TrackGirls&lt;/a&gt; &lt;a href=\"/r/tractors\"&gt;r/tractors&lt;/a&gt; &lt;a href=\"/r/tradclimbing\"&gt;r/tradclimbing&lt;/a&gt; &lt;a href=\"/r/TRADE\"&gt;r/TRADE&lt;/a&gt; &lt;a href=\"/r/tradfri\"&gt;r/tradfri&lt;/a&gt; &lt;a href=\"/r/Traeger\"&gt;r/Traeger&lt;/a&gt; &lt;a href=\"/r/traingifs\"&gt;r/traingifs&lt;/a&gt; &lt;a href=\"/r/Trainwreckstv\"&gt;r/Trainwreckstv&lt;/a&gt; &lt;a href=\"/r/transcribe\"&gt;r/transcribe&lt;/a&gt; &lt;a href=\"/r/transfashionadvice\"&gt;r/transfashionadvice&lt;/a&gt; &lt;a href=\"/r/transitiongoals\"&gt;r/transitiongoals&lt;/a&gt; &lt;a href=\"/r/translation\"&gt;r/translation&lt;/a&gt; &lt;a href=\"/r/TranslationStudies\"&gt;r/TranslationStudies&lt;/a&gt; &lt;a href=\"/r/Transmatfiring\"&gt;r/Transmatfiring&lt;/a&gt; &lt;a href=\"/r/TransportFever\"&gt;r/TransportFever&lt;/a&gt; &lt;a href=\"/r/TransSupport\"&gt;r/TransSupport&lt;/a&gt; &lt;a href=\"/r/TransyTalk\"&gt;r/TransyTalk&lt;/a&gt; &lt;a href=\"/r/trashyladyboners\"&gt;r/trashyladyboners&lt;/a&gt; &lt;a href=\"/r/Travala\"&gt;r/Travala&lt;/a&gt; &lt;a href=\"/r/Travel_Guide\"&gt;r/Travel_Guide&lt;/a&gt; &lt;a href=\"/r/travelphotos\"&gt;r/travelphotos&lt;/a&gt; &lt;a href=\"/r/treecipes\"&gt;r/treecipes&lt;/a&gt; &lt;a href=\"/r/treemovies\"&gt;r/treemovies&lt;/a&gt; &lt;a href=\"/r/treon\"&gt;r/treon&lt;/a&gt; &lt;a href=\"/r/TrialsGames\"&gt;r/TrialsGames&lt;/a&gt; &lt;a href=\"/r/Triangl\"&gt;r/Triangl&lt;/a&gt; &lt;a href=\"/r/trichotillomania\"&gt;r/trichotillomania&lt;/a&gt; &lt;a href=\"/r/Trichsters\"&gt;r/Trichsters&lt;/a&gt; &lt;a href=\"/r/Tricking\"&gt;r/Tricking&lt;/a&gt; &lt;a href=\"/r/Tripio\"&gt;r/Tripio&lt;/a&gt; &lt;a href=\"/r/triplej\"&gt;r/triplej&lt;/a&gt; &lt;a href=\"/r/trippingthroughtime\"&gt;r/trippingthroughtime&lt;/a&gt; &lt;a href=\"/r/tripreports\"&gt;r/tripreports&lt;/a&gt; &lt;a href=\"/r/trivia\"&gt;r/trivia&lt;/a&gt; &lt;a href=\"/r/TrollAnxiety\"&gt;r/TrollAnxiety&lt;/a&gt; &lt;a href=\"/r/trollbi\"&gt;r/trollbi&lt;/a&gt; &lt;a href=\"/r/trollfitness\"&gt;r/trollfitness&lt;/a&gt; &lt;a href=\"/r/trollingforababy\"&gt;r/trollingforababy&lt;/a&gt; &lt;a href=\"/r/TrollXFitness\"&gt;r/TrollXFitness&lt;/a&gt; &lt;a href=\"/r/TrollXGirlGamers\"&gt;r/TrollXGirlGamers&lt;/a&gt; &lt;a href=\"/r/TrollXOver30\"&gt;r/TrollXOver30&lt;/a&gt; &lt;a href=\"/r/TrollXWeddings\"&gt;r/TrollXWeddings&lt;/a&gt; &lt;a href=\"/r/Trombone\"&gt;r/Trombone&lt;/a&gt; &lt;a href=\"/r/tron\"&gt;r/tron&lt;/a&gt; &lt;a href=\"/r/Tropical\"&gt;r/Tropical&lt;/a&gt; &lt;a href=\"/r/troubledteens\"&gt;r/troubledteens&lt;/a&gt; &lt;a href=\"/r/troutfishing\"&gt;r/troutfishing&lt;/a&gt; &lt;a href=\"/r/TroveCreations\"&gt;r/TroveCreations&lt;/a&gt; &lt;a href=\"/r/trpgame\"&gt;r/trpgame&lt;/a&gt; &lt;a href=\"/r/TrueCinematography\"&gt;r/TrueCinematography&lt;/a&gt; &lt;a href=\"/r/truecreepyPMs\"&gt;r/truecreepyPMs&lt;/a&gt; &lt;a href=\"/r/TrueCrimeGarage\"&gt;r/TrueCrimeGarage&lt;/a&gt; &lt;a href=\"/r/truedocumentaries\"&gt;r/truedocumentaries&lt;/a&gt; &lt;a href=\"/r/truelesbians\"&gt;r/truelesbians&lt;/a&gt; &lt;a href=\"/r/truenews\"&gt;r/truenews&lt;/a&gt; &lt;a href=\"/r/TrueNorthPictures\"&gt;r/TrueNorthPictures&lt;/a&gt; &lt;a href=\"/r/TruePokemon\"&gt;r/TruePokemon&lt;/a&gt; &lt;a href=\"/r/Trumpgrets\"&gt;r/Trumpgrets&lt;/a&gt; &lt;a href=\"/r/TrumpNicknames\"&gt;r/TrumpNicknames&lt;/a&gt; &lt;a href=\"/r/TrumpRoasts\"&gt;r/TrumpRoasts&lt;/a&gt; &lt;a href=\"/r/trumptweets\"&gt;r/trumptweets&lt;/a&gt; &lt;a href=\"/r/TRXTrading\"&gt;r/TRXTrading&lt;/a&gt; &lt;a href=\"/r/TryndamereMains\"&gt;r/TryndamereMains&lt;/a&gt; &lt;a href=\"/r/TryNotToLaughYouLose\"&gt;r/TryNotToLaughYouLose&lt;/a&gt; &lt;a href=\"/r/TRYONBIKINI\"&gt;r/TRYONBIKINI&lt;/a&gt; &lt;a href=\"/r/tryonhaul\"&gt;r/tryonhaul&lt;/a&gt; &lt;a href=\"/r/TShirt\"&gt;r/TShirt&lt;/a&gt; &lt;a href=\"/r/ttcafterloss\"&gt;r/ttcafterloss&lt;/a&gt; &lt;a href=\"/r/tubetop\"&gt;r/tubetop&lt;/a&gt; &lt;a href=\"/r/tuesday\"&gt;r/tuesday&lt;/a&gt; &lt;a href=\"/r/TumblrPls\"&gt;r/TumblrPls&lt;/a&gt; &lt;a href=\"/r/TuringNet\"&gt;r/TuringNet&lt;/a&gt; &lt;a href=\"/r/Turntablists\"&gt;r/Turntablists&lt;/a&gt; &lt;a href=\"/r/turtles\"&gt;r/turtles&lt;/a&gt; &lt;a href=\"/r/turtleswithjobs\"&gt;r/turtleswithjobs&lt;/a&gt; &lt;a href=\"/r/tvtropes\"&gt;r/tvtropes&lt;/a&gt; &lt;a href=\"/r/TVZionApp\"&gt;r/TVZionApp&lt;/a&gt; &lt;a href=\"/r/TweakBounty\"&gt;r/TweakBounty&lt;/a&gt; &lt;a href=\"/r/TweakBoxApp\"&gt;r/TweakBoxApp&lt;/a&gt; &lt;a href=\"/r/twerknsfw\"&gt;r/twerknsfw&lt;/a&gt; &lt;a href=\"/r/twicememes\"&gt;r/twicememes&lt;/a&gt; &lt;a href=\"/r/twilightimperium\"&gt;r/twilightimperium&lt;/a&gt; &lt;a href=\"/r/twintails\"&gt;r/twintails&lt;/a&gt; &lt;a href=\"/r/TwitchMains\"&gt;r/TwitchMains&lt;/a&gt; &lt;a href=\"/r/twitchstreams\"&gt;r/twitchstreams&lt;/a&gt; &lt;a href=\"/r/twitter_memes\"&gt;r/twitter_memes&lt;/a&gt; &lt;a href=\"/r/TwoPointHospital\"&gt;r/TwoPointHospital&lt;/a&gt; &lt;a href=\"/r/TwoXADHD\"&gt;r/TwoXADHD&lt;/a&gt; &lt;a href=\"/r/TWRP\"&gt;r/TWRP&lt;/a&gt; &lt;a href=\"/r/tyingherhairup\"&gt;r/tyingherhairup&lt;/a&gt; &lt;a href=\"/r/typemoon\"&gt;r/typemoon&lt;/a&gt; &lt;a href=\"/r/typewriters\"&gt;r/typewriters&lt;/a&gt; &lt;a href=\"/r/TyrannyGame\"&gt;r/TyrannyGame&lt;/a&gt; &lt;a href=\"/r/tzuyu\"&gt;r/tzuyu&lt;/a&gt;&lt;/p&gt;\n&lt;/div&gt;&lt;!-- SC_ON --&gt;",
            "likes": null,
            "suggested_sort": "qa",
            "banned_at_utc": null,
            "view_count": null,
            "archived": true,
            "no_follow": false,
            "is_crosspostable": false,
            "pinned": false,
            "over_18": false,
            "all_awardings": [],
            "awarders": [],
            "media_only": false,
            "can_gild": false,
            "spoiler": false,
            "locked": false,
            "author_flair_text": null,
            "treatment_tags": [],
            "visited": false,
            "removed_by": null,
            "num_reports": null,
            "distinguished": null,
            "subreddit_id": "t5_eieek",
            "author_is_blocked": false,
            "mod_reason_by": null,
            "removal_reason": null,
            "link_flair_background_color": "",
            "id": "csc7hs",
            "is_robot_indexable": true,
            "num_duplicates": 0,
            "report_reasons": null,
            "author": "j259awesome",
            "discussion_type": null,
            "num_comments": 0,
            "send_replies": true,
            "media": null,
            "contest_mode": false,
            "author_patreon_flair": false,
            "author_flair_text_color": null,
            "permalink": "/r/u_j259awesome/comments/csc7hs/rt_5k10k/",
            "whitelist_status": null,
            "stickied": false,
            "url": "https://www.reddit.com/r/u_j259awesome/comments/csc7hs/rt_5k10k/",
            "subreddit_subscribers": 0,
            "created_utc": 1566189384.0,
            "num_crossposts": 0,
            "mod_reports": [],
            "is_video": false
          }
        }
      ],
      "before": null
    }
  },
  {
    "kind": "Listing",
    "data": {
      "after": null,
      "dist": null,
      "modhash": "",
      "geo_filter": "",
      "children": [],
      "before": null
    }
  }
]
